{"code":0,"message":"0","ttl":1,"data":{"bvid":"BV124411a7BZ","aid":52364221,"videos":34,"tid":208,"tname":"校园学习","copyright":1,"pic":"http://i1.hdslb.com/bfs/archive/8634cc88ebbd7c6053c7106f5ce7c6aa70cfeef2.jpg","title":"2天吃透Maven项目管理工具","pubdate":1557742465,"ctime":1557742465,"desc":"教程知识点\nmaven项目标准目录结构、\nmaven常用命令、\nmaven生命周期、\nmaven依赖作用范围、\nmaven概念模型、\nmaven传递依赖冲突解决、\n通过maven开发项目，\n对项目进行拆分、聚合、私服等。\n视频教程资料出自http://yun.itheima.com/course/234.html?bili","desc_v2":[{"raw_text":"教程知识点\nmaven项目标准目录结构、\nmaven常用命令、\nmaven生命周期、\nmaven依赖作用范围、\nmaven概念模型、\nmaven传递依赖冲突解决、\n通过maven开发项目，\n对项目进行拆分、聚合、私服等。\n视频教程资料出自http://yun.itheima.com/course/234.html?bili","type":1,"biz_id":0}],"state":0,"duration":23314,"rights":{"bp":0,"elec":0,"download":1,"movie":0,"pay":0,"hd5":0,"no_reprint":1,"autoplay":1,"ugc_pay":0,"is_cooperation":0,"ugc_pay_preview":0,"no_background":0,"clean_mode":0,"is_stein_gate":0,"is_360":0,"no_share":0,"arc_pay":0,"free_watch":0},"owner":{"mid":37974444,"name":"黑马程序员","face":"https://i0.hdslb.com/bfs/face/a71b4dd6647ddf0c813bcf74e062edab9224cb0e.jpg"},"stat":{"aid":52364221,"view":59614,"danmaku":69,"reply":39,"favorite":3267,"coin":271,"share":289,"now_rank":0,"his_rank":0,"like":480,"dislike":0,"evaluation":"","argue_msg":"","vt":0},"dynamic":"#maven##java##项目管理工具#","cid":91645149,"dimension":{"width":1920,"height":1080,"rotate":0},"premiere":null,"teenage_mode":0,"is_chargeable_season":false,"is_story":false,"is_upower_exclusive":false,"is_upower_play":false,"enable_vt":0,"vt_display":"","no_cache":false,"pages":[{"cid":91645149,"page":1,"from":"vupload","part":"01maven依赖管理","duration":957,"vid":"","weblink":"","dimension":{"width":1920,"height":1080,"rotate":0}},{"cid":91645205,"page":2,"from":"vupload","part":"02maven项目构建","duration":612,"vid":"","weblink":"","dimension":{"width":1366,"height":768,"rotate":0}},{"cid":91645278,"page":3,"from":"vupload","part":"03maven程序安装","duration":591,"vid":"","weblink":"","dimension":{"width":1366,"height":768,"rotate":0}},{"cid":91645363,"page":4,"from":"vupload","part":"04maven仓库类型","duration":638,"vid":"","weblink":"","dimension":{"width":1366,"height":768,"rotate":0}},{"cid":91645433,"page":5,"from":"vupload","part":"05配置maven本地仓库","duration":329,"vid":"","weblink":"","dimension":{"width":1366,"height":768,"rotate":0}},{"cid":91645504,"page":6,"from":"vupload","part":"06maven项目标准目录结构","duration":892,"vid":"","weblink":"","dimension":{"width":1366,"height":768,"rotate":0}},{"cid":91645639,"page":7,"from":"vupload","part":"07maven的常用命令","duration":1278,"vid":"","weblink":"","dimension":{"width":1366,"height":768,"rotate":0}},{"cid":91645827,"page":8,"from":"vupload","part":"08maven的生命周期","duration":354,"vid":"","weblink":"","dimension":{"width":1366,"height":768,"rotate":0}},{"cid":91645874,"page":9,"from":"vupload","part":"09在eclipse中配置maven插件","duration":668,"vid":"","weblink":"","dimension":{"width":1366,"height":768,"rotate":0}},{"cid":91645981,"page":10,"from":"vupload","part":"10创建maven项目\u0026查找依赖","duration":1545,"vid":"","weblink":"","dimension":{"width":1366,"height":768,"rotate":0}},{"cid":91646226,"page":11,"from":"vupload","part":"11依赖范围","duration":650,"vid":"","weblink":"","dimension":{"width":1366,"height":768,"rotate":0}},{"cid":91646354,"page":12,"from":"vupload","part":"12运行调试maven项目","duration":478,"vid":"","weblink":"","dimension":{"width":1366,"height":768,"rotate":0}},{"cid":91646431,"page":13,"from":"vupload","part":"13maven整合struts2","duration":1109,"vid":"","weblink":"","dimension":{"width":1366,"height":768,"rotate":0}},{"cid":91646705,"page":14,"from":"vupload","part":"14maven的概念模型","duration":217,"vid":"","weblink":"","dimension":{"width":1366,"height":768,"rotate":0}},{"cid":91646759,"page":15,"from":"vupload","part":"15总结","duration":472,"vid":"","weblink":"","dimension":{"width":1920,"height":1080,"rotate":0}},{"cid":91646795,"page":16,"from":"vupload","part":"01传递依赖冲突解决-maven自己调解原则","duration":885,"vid":"","weblink":"","dimension":{"width":1920,"height":1080,"rotate":0}},{"cid":91646881,"page":17,"from":"vupload","part":"02传递依赖冲突解决-排除依赖\u0026版本锁定","duration":808,"vid":"","weblink":"","dimension":{"width":1366,"height":768,"rotate":0}},{"cid":91647014,"page":18,"from":"vupload","part":"03ssh配置文件加载过程","duration":809,"vid":"","weblink":"","dimension":{"width":1366,"height":768,"rotate":0}},{"cid":91647097,"page":19,"from":"vupload","part":"04ssh整合-分别搭建环境","duration":631,"vid":"","weblink":"","dimension":{"width":1366,"height":768,"rotate":0}},{"cid":91647196,"page":20,"from":"vupload","part":"05ssh整合-struts2跟spring框架整合","duration":365,"vid":"","weblink":"","dimension":{"width":1366,"height":768,"rotate":0}},{"cid":91647246,"page":21,"from":"vupload","part":"06ssh整合-spring跟Hibernate框架整合","duration":1353,"vid":"","weblink":"","dimension":{"width":1366,"height":768,"rotate":0}},{"cid":91647444,"page":22,"from":"vupload","part":"07ssh整合功能案例实现","duration":1572,"vid":"","weblink":"","dimension":{"width":1366,"height":768,"rotate":0}},{"cid":91647756,"page":23,"from":"vupload","part":"08项目拆分-创建父工程","duration":735,"vid":"","weblink":"","dimension":{"width":1366,"height":768,"rotate":0}},{"cid":91647854,"page":24,"from":"vupload","part":"09项目拆分-创建子模块ssh-dao","duration":550,"vid":"","weblink":"","dimension":{"width":1366,"height":768,"rotate":0}},{"cid":91647960,"page":25,"from":"vupload","part":"10项目拆分-创建子模块ssh-service","duration":350,"vid":"","weblink":"","dimension":{"width":1366,"height":768,"rotate":0}},{"cid":91648009,"page":26,"from":"vupload","part":"11项目拆分-创建子模块ssh-web","duration":296,"vid":"","weblink":"","dimension":{"width":1366,"height":768,"rotate":0}},{"cid":91648080,"page":27,"from":"vupload","part":"12传递依赖的范围","duration":1206,"vid":"","weblink":"","dimension":{"width":1366,"height":768,"rotate":0}},{"cid":91648289,"page":28,"from":"vupload","part":"13运行的方式","duration":366,"vid":"","weblink":"","dimension":{"width":1366,"height":768,"rotate":0}},{"cid":91648371,"page":29,"from":"vupload","part":"14私服安装","duration":606,"vid":"","weblink":"","dimension":{"width":1366,"height":768,"rotate":0}},{"cid":91648458,"page":30,"from":"vupload","part":"15私服上仓库类型","duration":379,"vid":"","weblink":"","dimension":{"width":1366,"height":768,"rotate":0}},{"cid":91648506,"page":31,"from":"vupload","part":"16上传jar包到私服","duration":552,"vid":"","weblink":"","dimension":{"width":1366,"height":768,"rotate":0}},{"cid":91648625,"page":32,"from":"vupload","part":"17从私服上下载jar包到本地仓库","duration":514,"vid":"","weblink":"","dimension":{"width":1366,"height":768,"rotate":0}},{"cid":91648752,"page":33,"from":"vupload","part":"18总结","duration":126,"vid":"","weblink":"","dimension":{"width":1366,"height":768,"rotate":0}},{"cid":91648770,"page":34,"from":"vupload","part":"19maven的好处avi","duration":421,"vid":"","weblink":"","dimension":{"width":1920,"height":1080,"rotate":0}}],"subtitle":{"allow_submit":false,"list":[]},"is_season_display":false,"user_garb":{"url_image_ani_cut":""},"honor_reply":{},"like_icon":"","need_jump_bv":false,"disable_show_up_info":false}}