{"code":0,"message":"0","ttl":1,"data":{"bvid":"BV1Qo4y1d7nz","aid":373565229,"videos":49,"tid":209,"tname":"职业职场","copyright":1,"pic":"http://i1.hdslb.com/bfs/archive/8b19770df7be3c1beb9cb078bc35a18d0a06a60f.jpg","title":"黑马程序员新媒体教程零基础玩转短视频抖音，轻松实现流量变现","pubdate":1610329270,"ctime":1610244856,"desc":"零基础玩转短视频平台，喜欢小伙伴们三连哟。\n抖音带货的崛起让更多自媒体人有了选择，创业成本降低，人人都是自媒体。","desc_v2":[{"raw_text":"零基础玩转短视频平台，喜欢小伙伴们三连哟。\n抖音带货的崛起让更多自媒体人有了选择，创业成本降低，人人都是自媒体。","type":1,"biz_id":0}],"state":0,"duration":32791,"mission_id":15417,"rights":{"bp":0,"elec":0,"download":1,"movie":0,"pay":0,"hd5":0,"no_reprint":1,"autoplay":1,"ugc_pay":0,"is_cooperation":0,"ugc_pay_preview":0,"no_background":0,"clean_mode":0,"is_stein_gate":0,"is_360":0,"no_share":0,"arc_pay":0,"free_watch":0},"owner":{"mid":37974444,"name":"黑马程序员","face":"https://i0.hdslb.com/bfs/face/a71b4dd6647ddf0c813bcf74e062edab9224cb0e.jpg"},"stat":{"aid":373565229,"view":29852,"danmaku":132,"reply":40,"favorite":1779,"coin":317,"share":674,"now_rank":0,"his_rank":0,"like":565,"dislike":0,"evaluation":"","argue_msg":"","vt":0},"dynamic":"","cid":280464227,"dimension":{"width":1920,"height":1080,"rotate":0},"premiere":null,"teenage_mode":0,"is_chargeable_season":false,"is_story":false,"is_upower_exclusive":false,"is_upower_play":false,"enable_vt":0,"vt_display":"","no_cache":false,"pages":[{"cid":280464227,"page":1,"from":"vupload","part":"01-新媒体认知","duration":241,"vid":"","weblink":"","dimension":{"width":1920,"height":1080,"rotate":0}},{"cid":280464239,"page":2,"from":"vupload","part":"02-新媒体就业前景","duration":249,"vid":"","weblink":"","dimension":{"width":1920,"height":1080,"rotate":0}},{"cid":280464299,"page":3,"from":"vupload","part":"03-新媒体薪资待遇","duration":385,"vid":"","weblink":"","dimension":{"width":1920,"height":1080,"rotate":0}},{"cid":280464311,"page":4,"from":"vupload","part":"04-0基础创业与副业刚需","duration":686,"vid":"","weblink":"","dimension":{"width":1920,"height":1080,"rotate":0}},{"cid":280464458,"page":5,"from":"vupload","part":"05-新媒体运营核心三个步骤","duration":251,"vid":"","weblink":"","dimension":{"width":1920,"height":1080,"rotate":0}},{"cid":280464489,"page":6,"from":"vupload","part":"06-不同的步骤在实际运营中的体现","duration":728,"vid":"","weblink":"","dimension":{"width":1920,"height":1080,"rotate":0}},{"cid":280464669,"page":7,"from":"vupload","part":"07-100000+播放账号分析之威希第","duration":676,"vid":"","weblink":"","dimension":{"width":1920,"height":1080,"rotate":0}},{"cid":280464839,"page":8,"from":"vupload","part":"08-100000 播放账号分析之隔壁老舅","duration":422,"vid":"","weblink":"","dimension":{"width":1920,"height":1080,"rotate":0}},{"cid":280464872,"page":9,"from":"vupload","part":"01-10分钟做出搬运账号","duration":1288,"vid":"","weblink":"","dimension":{"width":1920,"height":1080,"rotate":0}},{"cid":280464960,"page":10,"from":"vupload","part":"02-人人可上手的影视剪辑类账号（1）","duration":944,"vid":"","weblink":"","dimension":{"width":1920,"height":1080,"rotate":0}},{"cid":280465686,"page":11,"from":"vupload","part":"04-vlog概念","duration":230,"vid":"","weblink":"","dimension":{"width":1920,"height":1080,"rotate":0}},{"cid":280465715,"page":12,"from":"vupload","part":"05-日常VLOG速成写作公式","duration":972,"vid":"","weblink":"","dimension":{"width":1920,"height":1080,"rotate":0}},{"cid":280465807,"page":13,"from":"vupload","part":"06-美食VLOG速成写作公式","duration":434,"vid":"","weblink":"","dimension":{"width":1920,"height":1080,"rotate":0}},{"cid":280465997,"page":14,"from":"vupload","part":"07-旅行VLOG速成写作公式","duration":849,"vid":"","weblink":"","dimension":{"width":1920,"height":1080,"rotate":0}},{"cid":280466154,"page":15,"from":"vupload","part":"08-vlog总结","duration":208,"vid":"","weblink":"","dimension":{"width":1920,"height":1080,"rotate":0}},{"cid":280466165,"page":16,"from":"vupload","part":"09-知识分享结构一","duration":715,"vid":"","weblink":"","dimension":{"width":1920,"height":1080,"rotate":0}},{"cid":280466234,"page":17,"from":"vupload","part":"10-知识分享结构二","duration":411,"vid":"","weblink":"","dimension":{"width":1920,"height":1080,"rotate":0}},{"cid":280466290,"page":18,"from":"vupload","part":"11-知识分享类视频总结","duration":141,"vid":"","weblink":"","dimension":{"width":1920,"height":1080,"rotate":0}},{"cid":280466307,"page":19,"from":"vupload","part":"12-营销账号最新玩法","duration":903,"vid":"","weblink":"","dimension":{"width":1920,"height":1080,"rotate":0}},{"cid":280466356,"page":20,"from":"vupload","part":"01-抖音的赛马机制","duration":918,"vid":"","weblink":"","dimension":{"width":1920,"height":1080,"rotate":0}},{"cid":280466390,"page":21,"from":"vupload","part":"02-养号及100%破播放","duration":924,"vid":"","weblink":"","dimension":{"width":1920,"height":1080,"rotate":0}},{"cid":280466525,"page":22,"from":"vupload","part":"03-账号被关进小黑屋脱坑破解法","duration":481,"vid":"","weblink":"","dimension":{"width":1920,"height":1080,"rotate":0}},{"cid":280466551,"page":23,"from":"vupload","part":"04-10种标题撰写公式","duration":815,"vid":"","weblink":"","dimension":{"width":1920,"height":1080,"rotate":0}},{"cid":280466716,"page":24,"from":"vupload","part":"05-10种标题撰写公式","duration":1191,"vid":"","weblink":"","dimension":{"width":1920,"height":1080,"rotate":0}},{"cid":280466758,"page":25,"from":"vupload","part":"06-为短视频埋藏深水炸弹","duration":1242,"vid":"","weblink":"","dimension":{"width":1920,"height":1080,"rotate":0}},{"cid":280466827,"page":26,"from":"vupload","part":"01-短视频工具详讲","duration":532,"vid":"","weblink":"","dimension":{"width":1920,"height":1080,"rotate":0}},{"cid":280466845,"page":27,"from":"vupload","part":"02-如何处理声音","duration":791,"vid":"","weblink":"","dimension":{"width":1920,"height":1080,"rotate":0}},{"cid":280467041,"page":28,"from":"vupload","part":"03-剪映剪同款","duration":442,"vid":"","weblink":"","dimension":{"width":1920,"height":1080,"rotate":0}},{"cid":280467074,"page":29,"from":"vupload","part":"04-界面认识","duration":425,"vid":"","weblink":"","dimension":{"width":1920,"height":1080,"rotate":0}},{"cid":280467097,"page":30,"from":"vupload","part":"05-导入素材剪辑素材","duration":899,"vid":"","weblink":"","dimension":{"width":1920,"height":1080,"rotate":0}},{"cid":280467143,"page":31,"from":"vupload","part":"06-特效制作","duration":1021,"vid":"","weblink":"","dimension":{"width":1920,"height":1080,"rotate":0}},{"cid":280467188,"page":32,"from":"vupload","part":"07-添加音频","duration":370,"vid":"","weblink":"","dimension":{"width":1920,"height":1080,"rotate":0}},{"cid":280467210,"page":33,"from":"vupload","part":"08-添加字幕","duration":955,"vid":"","weblink":"","dimension":{"width":1920,"height":1080,"rotate":0}},{"cid":280467243,"page":34,"from":"vupload","part":"01-PR的5大界面","duration":765,"vid":"","weblink":"","dimension":{"width":1920,"height":1080,"rotate":0}},{"cid":280467276,"page":35,"from":"vupload","part":"02-工作流程","duration":598,"vid":"","weblink":"","dimension":{"width":1920,"height":1080,"rotate":0}},{"cid":280467301,"page":36,"from":"vupload","part":"03-工作流程之新建项目（厨房）","duration":357,"vid":"","weblink":"","dimension":{"width":1920,"height":1080,"rotate":0}},{"cid":280467405,"page":37,"from":"vupload","part":"04-工作流程之导入素材（拿菜）","duration":235,"vid":"","weblink":"","dimension":{"width":1920,"height":1080,"rotate":0}},{"cid":280467448,"page":38,"from":"vupload","part":"05-工作流程之新建序列（菜板）","duration":487,"vid":"","weblink":"","dimension":{"width":1920,"height":1080,"rotate":0}},{"cid":280467572,"page":39,"from":"vupload","part":"06-工作流程之剪辑生成","duration":799,"vid":"","weblink":"","dimension":{"width":1920,"height":1080,"rotate":0}},{"cid":280467943,"page":40,"from":"vupload","part":"07-核心功能剪辑","duration":1053,"vid":"","weblink":"","dimension":{"width":1920,"height":1080,"rotate":0}},{"cid":280468151,"page":41,"from":"vupload","part":"08-视频调色","duration":415,"vid":"","weblink":"","dimension":{"width":1920,"height":1080,"rotate":0}},{"cid":280468188,"page":42,"from":"vupload","part":"09-如何给视频添加字幕","duration":935,"vid":"","weblink":"","dimension":{"width":1920,"height":1080,"rotate":0}},{"cid":280468378,"page":43,"from":"vupload","part":"10-利用beautybox进行人像调整","duration":628,"vid":"","weblink":"","dimension":{"width":1920,"height":1080,"rotate":0}},{"cid":280468538,"page":44,"from":"vupload","part":"11-美食教学调剪","duration":883,"vid":"","weblink":"","dimension":{"width":1920,"height":1080,"rotate":0}},{"cid":280468596,"page":45,"from":"vupload","part":"01-测试类账号玩法及变现（1）","duration":957,"vid":"","weblink":"","dimension":{"width":1920,"height":1080,"rotate":0}},{"cid":280468844,"page":46,"from":"vupload","part":"02-测试类账号玩法及变现（2）","duration":458,"vid":"","weblink":"","dimension":{"width":1920,"height":1080,"rotate":0}},{"cid":280468955,"page":47,"from":"vupload","part":"03-老照片修复类账号制作变现玩法","duration":683,"vid":"","weblink":"","dimension":{"width":1920,"height":1080,"rotate":0}},{"cid":280469005,"page":48,"from":"vupload","part":"04-表情包视频账号制作变现玩法","duration":916,"vid":"","weblink":"","dimension":{"width":1920,"height":1080,"rotate":0}},{"cid":280469046,"page":49,"from":"vupload","part":"05-抖音电商变现体系搭建","duration":883,"vid":"","weblink":"","dimension":{"width":1920,"height":1080,"rotate":0}}],"subtitle":{"allow_submit":false,"list":[]},"is_season_display":false,"user_garb":{"url_image_ani_cut":""},"honor_reply":{},"like_icon":"","need_jump_bv":false,"disable_show_up_info":false}}