{"code":0,"message":"0","ttl":1,"data":{"bvid":"BV1VE411h7aL","aid":73730658,"videos":49,"tid":231,"tname":"计算机技术","copyright":1,"pic":"http://i1.hdslb.com/bfs/archive/7390fea234fd80b87e47c1f861650bcfcb60ed0c.png","title":"黑马程序员Java进阶教程快速入门Spring Security OAuth2.0认证授权","pubdate":1572253344,"ctime":1572253344,"desc":"认证和授权是解决软件系统安全的两个基础概念，认证是校验使用者的身份是否合法，授权是校验使用者是否拥有操作资源的权限。互联网的发展也促进了软件开放性设计的进步，软件既要开放又要安全，如何使用统一的方案解决软件自身及外部系统的认证需求是当前互联网应用要考虑的问题，OAuth2.0协议是当前开放流行的认证协议，本课程使用流行的Spring Security认证框架及OAuth2.0协议实现单体及分布式系统的认证授权技术解决方案。","desc_v2":[{"raw_text":"认证和授权是解决软件系统安全的两个基础概念，认证是校验使用者的身份是否合法，授权是校验使用者是否拥有操作资源的权限。互联网的发展也促进了软件开放性设计的进步，软件既要开放又要安全，如何使用统一的方案解决软件自身及外部系统的认证需求是当前互联网应用要考虑的问题，OAuth2.0协议是当前开放流行的认证协议，本课程使用流行的Spring Security认证框架及OAuth2.0协议实现单体及分布式系统的认证授权技术解决方案。","type":1,"biz_id":0}],"state":0,"duration":29978,"rights":{"bp":0,"elec":0,"download":1,"movie":0,"pay":0,"hd5":0,"no_reprint":1,"autoplay":1,"ugc_pay":0,"is_cooperation":0,"ugc_pay_preview":0,"no_background":0,"clean_mode":0,"is_stein_gate":0,"is_360":0,"no_share":0,"arc_pay":0,"free_watch":0},"owner":{"mid":37974444,"name":"黑马程序员","face":"https://i0.hdslb.com/bfs/face/a71b4dd6647ddf0c813bcf74e062edab9224cb0e.jpg"},"stat":{"aid":73730658,"view":481812,"danmaku":7548,"reply":477,"favorite":15237,"coin":2821,"share":1101,"now_rank":0,"his_rank":0,"like":3513,"dislike":0,"evaluation":"","argue_msg":"","vt":0},"dynamic":"","cid":126112030,"dimension":{"width":1920,"height":1080,"rotate":0},"premiere":null,"teenage_mode":0,"is_chargeable_season":false,"is_story":false,"is_upower_exclusive":false,"is_upower_play":false,"enable_vt":0,"vt_display":"","no_cache":false,"pages":[{"cid":126112030,"page":1,"from":"vupload","part":"01.认证授权课程介绍","duration":457,"vid":"","weblink":"","dimension":{"width":1920,"height":1080,"rotate":0}},{"cid":126112064,"page":2,"from":"vupload","part":"02.基础概念-认证授权会话","duration":634,"vid":"","weblink":"","dimension":{"width":1364,"height":768,"rotate":0}},{"cid":126112121,"page":3,"from":"vupload","part":"03.基础概念-授权的数据模型","duration":792,"vid":"","weblink":"","dimension":{"width":1364,"height":768,"rotate":0}},{"cid":126112200,"page":4,"from":"vupload","part":"04.基础概念-RBAC","duration":454,"vid":"","weblink":"","dimension":{"width":1364,"height":768,"rotate":0}},{"cid":126112249,"page":5,"from":"vupload","part":"05.基于Session的认证方式-认证流程","duration":186,"vid":"","weblink":"","dimension":{"width":1364,"height":768,"rotate":0}},{"cid":126112276,"page":6,"from":"vupload","part":"06.基于Session的认证方式-创建工程","duration":864,"vid":"","weblink":"","dimension":{"width":1364,"height":768,"rotate":0}},{"cid":126112320,"page":7,"from":"vupload","part":"07.基于Session的认证方式-实现认证功能","duration":927,"vid":"","weblink":"","dimension":{"width":1364,"height":768,"rotate":0}},{"cid":126112381,"page":8,"from":"vupload","part":"08.基于Session的认证方式-实现会话功能","duration":417,"vid":"","weblink":"","dimension":{"width":1364,"height":768,"rotate":0}},{"cid":126112415,"page":9,"from":"vupload","part":"09.基于Session的认证方式-实现授权功能","duration":1004,"vid":"","weblink":"","dimension":{"width":1364,"height":768,"rotate":0}},{"cid":126112472,"page":10,"from":"vupload","part":"10.Spring Security-创建工程","duration":396,"vid":"","weblink":"","dimension":{"width":1364,"height":768,"rotate":0}},{"cid":126112497,"page":11,"from":"vupload","part":"11.Spring Security-认证功能","duration":1077,"vid":"","weblink":"","dimension":{"width":1364,"height":768,"rotate":0}},{"cid":126112551,"page":12,"from":"vupload","part":"12.Spring Security-授权功能","duration":284,"vid":"","weblink":"","dimension":{"width":1364,"height":768,"rotate":0}},{"cid":126112576,"page":13,"from":"vupload","part":"13.Spring -SpringBoot","duration":710,"vid":"","weblink":"","dimension":{"width":1364,"height":768,"rotate":0}},{"cid":126112623,"page":14,"from":"vupload","part":"14.Spring Security-结构总览","duration":458,"vid":"","weblink":"","dimension":{"width":1364,"height":768,"rotate":0}},{"cid":126112676,"page":15,"from":"vupload","part":"15.Spring Security-认证流程","duration":728,"vid":"","weblink":"","dimension":{"width":1364,"height":768,"rotate":0}},{"cid":126112728,"page":16,"from":"vupload","part":"16.UserDetailService","duration":821,"vid":"","weblink":"","dimension":{"width":1364,"height":768,"rotate":0}},{"cid":126112810,"page":17,"from":"vupload","part":"17.工作原理-PasswordEncoder","duration":642,"vid":"","weblink":"","dimension":{"width":1364,"height":768,"rotate":0}},{"cid":126112874,"page":18,"from":"vupload","part":"18.工作原理-授权流程","duration":482,"vid":"","weblink":"","dimension":{"width":1364,"height":768,"rotate":0}},{"cid":126112911,"page":19,"from":"vupload","part":"19.自定义登录页面","duration":697,"vid":"","weblink":"","dimension":{"width":1364,"height":768,"rotate":0}},{"cid":126112951,"page":20,"from":"vupload","part":"20.-连接数据库认证","duration":921,"vid":"","weblink":"","dimension":{"width":1364,"height":768,"rotate":0}},{"cid":126112999,"page":21,"from":"vupload","part":"21.应用详解-会话管理","duration":663,"vid":"","weblink":"","dimension":{"width":1364,"height":768,"rotate":0}},{"cid":126113039,"page":22,"from":"vupload","part":"22.应用详解-自定义退出","duration":281,"vid":"","weblink":"","dimension":{"width":1364,"height":768,"rotate":0}},{"cid":126113062,"page":23,"from":"vupload","part":"23.连接数据库查权限","duration":896,"vid":"","weblink":"","dimension":{"width":1364,"height":768,"rotate":0}},{"cid":126113105,"page":24,"from":"vupload","part":"24.授权-web授权","duration":391,"vid":"","weblink":"","dimension":{"width":1364,"height":768,"rotate":0}},{"cid":126113148,"page":25,"from":"vupload","part":"25.授权-方法授权","duration":531,"vid":"","weblink":"","dimension":{"width":1920,"height":1080,"rotate":0}},{"cid":126113180,"page":26,"from":"vupload","part":"01.分布式系统认证方案-什么是分布式系统","duration":351,"vid":"","weblink":"","dimension":{"width":1920,"height":1080,"rotate":0}},{"cid":126113202,"page":27,"from":"vupload","part":"02.分布式系统认证方案-分布式认证需求","duration":419,"vid":"","weblink":"","dimension":{"width":1364,"height":768,"rotate":0}},{"cid":126113227,"page":28,"from":"vupload","part":"03.分布式系统认证方案-分布式认证方案","duration":614,"vid":"","weblink":"","dimension":{"width":1364,"height":768,"rotate":0}},{"cid":126113284,"page":29,"from":"vupload","part":"04.OAuth2.0-介绍","duration":855,"vid":"","weblink":"","dimension":{"width":1364,"height":768,"rotate":0}},{"cid":126113348,"page":30,"from":"vupload","part":"05.OAuth2.0-Spring Cloud Security OAuth2-环境介绍","duration":395,"vid":"","weblink":"","dimension":{"width":1364,"height":768,"rotate":0}},{"cid":126113390,"page":31,"from":"vupload","part":"06.OAuth2.0-Spring Cloud Security OAuth2-环境搭建","duration":737,"vid":"","weblink":"","dimension":{"width":1364,"height":768,"rotate":0}},{"cid":126113436,"page":32,"from":"vupload","part":"07.OAuth2.0-Spring Cloud Security OAuth2-授权服务配置","duration":1464,"vid":"","weblink":"","dimension":{"width":1364,"height":768,"rotate":0}},{"cid":126113548,"page":33,"from":"vupload","part":"08.OAuth2.0-Spring Cloud Security OAuth2-授权服务配置-三项内容","duration":474,"vid":"","weblink":"","dimension":{"width":1364,"height":768,"rotate":0}},{"cid":126113572,"page":34,"from":"vupload","part":"09.OAuth2.0-Spring Cloud Security OAuth2-授权服务配置-客户端详情配置","duration":486,"vid":"","weblink":"","dimension":{"width":1364,"height":768,"rotate":0}},{"cid":126113610,"page":35,"from":"vupload","part":"10.OAuth2.0-Spring Cloud Security OAuth2-授权服务配置-令牌服务和令牌端点配置","duration":982,"vid":"","weblink":"","dimension":{"width":1364,"height":768,"rotate":0}},{"cid":126113694,"page":36,"from":"vupload","part":"11.OAuth2.0-Spring Cloud Security OAuth2-授权码模式","duration":743,"vid":"","weblink":"","dimension":{"width":1364,"height":768,"rotate":0}},{"cid":126113751,"page":37,"from":"vupload","part":"12.OAuth2.0-Spring Cloud Security OAuth2-密码模式及其它模式","duration":462,"vid":"","weblink":"","dimension":{"width":1364,"height":768,"rotate":0}},{"cid":126113783,"page":38,"from":"vupload","part":"13.OAuth2.0-Spring Cloud Security OAuth2-资源服务测试","duration":849,"vid":"","weblink":"","dimension":{"width":1364,"height":768,"rotate":0}},{"cid":126113831,"page":39,"from":"vupload","part":"14.OAuth2.0-JWT令牌-介绍","duration":385,"vid":"","weblink":"","dimension":{"width":1364,"height":768,"rotate":0}},{"cid":126113873,"page":40,"from":"vupload","part":"15.OAuth2.0-JWT令牌-生成令牌和校验令牌","duration":519,"vid":"","weblink":"","dimension":{"width":1364,"height":768,"rotate":0}},{"cid":126113903,"page":41,"from":"vupload","part":"16.OAuth2.0-完善环境配置","duration":500,"vid":"","weblink":"","dimension":{"width":1364,"height":768,"rotate":0}},{"cid":126113945,"page":42,"from":"vupload","part":"17.Spring Security实现分布式认证授权-搭建注册中心","duration":489,"vid":"","weblink":"","dimension":{"width":1364,"height":768,"rotate":0}},{"cid":126113987,"page":43,"from":"vupload","part":"18.Spring Security实现分布式认证授权-搭建网关工程","duration":401,"vid":"","weblink":"","dimension":{"width":1364,"height":768,"rotate":0}},{"cid":126114020,"page":44,"from":"vupload","part":"19.Spring Security实现分布式认证授权-网关资源服务配置","duration":400,"vid":"","weblink":"","dimension":{"width":1364,"height":768,"rotate":0}},{"cid":126114057,"page":45,"from":"vupload","part":"20.Spring Security实现分布式认证授权-转发明文token给微服务","duration":876,"vid":"","weblink":"","dimension":{"width":1364,"height":768,"rotate":0}},{"cid":126114133,"page":46,"from":"vupload","part":"21.Spring Security实现分布式认证授权-微服务解析令牌并鉴权","duration":726,"vid":"","weblink":"","dimension":{"width":1364,"height":768,"rotate":0}},{"cid":126114190,"page":47,"from":"vupload","part":"22.Spring Security实现分布式认证授权-集成测试","duration":311,"vid":"","weblink":"","dimension":{"width":1364,"height":768,"rotate":0}},{"cid":126114218,"page":48,"from":"vupload","part":"23.Spring Security实现分布式认证授权-扩展用户信息","duration":441,"vid":"","weblink":"","dimension":{"width":1364,"height":768,"rotate":0}},{"cid":126114253,"page":49,"from":"vupload","part":"24.课程总结","duration":386,"vid":"","weblink":"","dimension":{"width":1920,"height":1080,"rotate":0}}],"subtitle":{"allow_submit":false,"list":[]},"is_season_display":false,"user_garb":{"url_image_ani_cut":""},"honor_reply":{},"like_icon":"","need_jump_bv":false,"disable_show_up_info":false}}