{"code":0,"message":"0","ttl":1,"data":{"bvid":"BV1yx411k7VT","aid":8915750,"videos":130,"tid":208,"tname":"校园学习","copyright":1,"pic":"http://i1.hdslb.com/bfs/archive/4e75b8111b24f708c61e11543451c09156158d8e.jpg","title":"亲情奉献全套精品.Net基础视频教程（1-9）","pubdate":1488415842,"ctime":1497436853,"desc":"本套教程为传智播客旗下高端教育品牌黑马程序员出品，黑马程序员官网为http://www.itheima.com/更多免费学习教程领取请关注黑马公众号itheima666，关注后回复教程两字即可领取相关教程视频+源码下载地址。","desc_v2":[{"raw_text":"本套教程为传智播客旗下高端教育品牌黑马程序员出品，黑马程序员官网为http://www.itheima.com/更多免费学习教程领取请关注黑马公众号itheima666，关注后回复教程两字即可领取相关教程视频+源码下载地址。","type":1,"biz_id":0}],"state":0,"duration":130116,"rights":{"bp":0,"elec":0,"download":1,"movie":0,"pay":0,"hd5":0,"no_reprint":0,"autoplay":1,"ugc_pay":0,"is_cooperation":0,"ugc_pay_preview":0,"no_background":0,"clean_mode":0,"is_stein_gate":0,"is_360":0,"no_share":0,"arc_pay":0,"free_watch":0},"owner":{"mid":37974444,"name":"黑马程序员","face":"https://i0.hdslb.com/bfs/face/a71b4dd6647ddf0c813bcf74e062edab9224cb0e.jpg"},"stat":{"aid":8915750,"view":76609,"danmaku":645,"reply":44,"favorite":2265,"coin":440,"share":500,"now_rank":0,"his_rank":0,"like":407,"dislike":0,"evaluation":"","argue_msg":"","vt":0},"dynamic":"","cid":14714630,"dimension":{"width":640,"height":360,"rotate":0},"premiere":null,"teenage_mode":0,"is_chargeable_season":false,"is_story":false,"is_upower_exclusive":false,"is_upower_play":false,"enable_vt":0,"vt_display":"","no_cache":false,"pages":[{"cid":14714630,"page":1,"from":"vupload","part":"day01-1、.Net平台","duration":536,"vid":"","weblink":"","dimension":{"width":640,"height":360,"rotate":0}},{"cid":14714631,"page":2,"from":"vupload","part":"day01-2、c#编程语言","duration":157,"vid":"","weblink":"","dimension":{"width":480,"height":360,"rotate":0}},{"cid":14714632,"page":3,"from":"vupload","part":"day01-3、.Net都能做什么","duration":230,"vid":"","weblink":"","dimension":{"width":480,"height":360,"rotate":0}},{"cid":14714633,"page":4,"from":"vupload","part":"day01-4、.Net两种交互模式","duration":102,"vid":"","weblink":"","dimension":{"width":480,"height":360,"rotate":0}},{"cid":14714634,"page":5,"from":"vupload","part":"day01-5、VS的各个组成部分","duration":1889,"vid":"","weblink":"","dimension":{"width":480,"height":360,"rotate":0}},{"cid":14714635,"page":6,"from":"vupload","part":"day01-6、两行代码","duration":693,"vid":"","weblink":"","dimension":{"width":480,"height":360,"rotate":0}},{"cid":14714636,"page":7,"from":"vupload","part":"day01-7、VS的基本设置","duration":950,"vid":"","weblink":"","dimension":{"width":480,"height":360,"rotate":0}},{"cid":14714637,"page":8,"from":"vupload","part":"day01-8、第一天 总结","duration":447,"vid":"","weblink":"","dimension":{"width":640,"height":360,"rotate":0}},{"cid":14714638,"page":9,"from":"vupload","part":"day02-1、c 中的注释符","duration":1104,"vid":"","weblink":"","dimension":{"width":640,"height":360,"rotate":0}},{"cid":14714639,"page":10,"from":"vupload","part":"day02-2、c#中常用的快捷键","duration":1110,"vid":"","weblink":"","dimension":{"width":480,"height":360,"rotate":0}},{"cid":14714640,"page":11,"from":"vupload","part":"day02-3、变量的存储以及变量的几种类型","duration":2066,"vid":"","weblink":"","dimension":{"width":480,"height":360,"rotate":0}},{"cid":14714641,"page":12,"from":"vupload","part":"day02-4、变量的使用规则","duration":450,"vid":"","weblink":"","dimension":{"width":480,"height":360,"rotate":0}},{"cid":14714642,"page":13,"from":"vupload","part":"day02-5、变量的命名规范","duration":1308,"vid":"","weblink":"","dimension":{"width":810,"height":608,"rotate":0}},{"cid":14714643,"page":14,"from":"vupload","part":"day02-6、赋值运算符","duration":389,"vid":"","weblink":"","dimension":{"width":480,"height":360,"rotate":0}},{"cid":14714644,"page":15,"from":"vupload","part":"day02-7、+号的使用","duration":465,"vid":"","weblink":"","dimension":{"width":480,"height":360,"rotate":0}},{"cid":14714645,"page":16,"from":"vupload","part":"day02-8、两个练习","duration":304,"vid":"","weblink":"","dimension":{"width":810,"height":608,"rotate":0}},{"cid":14714646,"page":17,"from":"vupload","part":"day02-9、占位符的使用","duration":1274,"vid":"","weblink":"","dimension":{"width":480,"height":360,"rotate":0}},{"cid":14714647,"page":18,"from":"vupload","part":"day02-10、交换变量","duration":1011,"vid":"","weblink":"","dimension":{"width":480,"height":360,"rotate":0}},{"cid":14714648,"page":19,"from":"vupload","part":"day02-11、接收用户的输入","duration":478,"vid":"","weblink":"","dimension":{"width":480,"height":360,"rotate":0}},{"cid":14714649,"page":20,"from":"vupload","part":"day02-12、接收用户的输入练习","duration":274,"vid":"","weblink":"","dimension":{"width":480,"height":360,"rotate":0}},{"cid":14714650,"page":21,"from":"vupload","part":"day02-13、c#中的转义符和@符号的作用","duration":1658,"vid":"","weblink":"","dimension":{"width":480,"height":360,"rotate":0}},{"cid":14714651,"page":22,"from":"vupload","part":"day02-14、算数运算符","duration":627,"vid":"","weblink":"","dimension":{"width":810,"height":608,"rotate":0}},{"cid":14714652,"page":23,"from":"vupload","part":"day02-15、显示类型转换和隐士类型转换","duration":1362,"vid":"","weblink":"","dimension":{"width":480,"height":360,"rotate":0}},{"cid":14714653,"page":24,"from":"vupload","part":"day02-16、总结","duration":662,"vid":"","weblink":"","dimension":{"width":640,"height":360,"rotate":0}},{"cid":14714654,"page":25,"from":"vupload","part":"day03-1、复习","duration":684,"vid":"","weblink":"","dimension":{"width":640,"height":360,"rotate":0}},{"cid":14714655,"page":26,"from":"vupload","part":"day03-2、两道练习题","duration":542,"vid":"","weblink":"","dimension":{"width":480,"height":360,"rotate":0}},{"cid":14743523,"page":27,"from":"vupload","part":"day03-3、Convert类型转换","duration":1291,"vid":"","weblink":"","dimension":{"width":480,"height":360,"rotate":0}},{"cid":14743524,"page":28,"from":"vupload","part":"day03-4、加加减减","duration":1587,"vid":"","weblink":"","dimension":{"width":480,"height":360,"rotate":0}},{"cid":14743525,"page":29,"from":"vupload","part":"day03-5、关系运算符和逻辑运算符","duration":1421,"vid":"","weblink":"","dimension":{"width":480,"height":360,"rotate":0}},{"cid":14743526,"page":30,"from":"vupload","part":"day03-6、判断闰年练习","duration":671,"vid":"","weblink":"","dimension":{"width":480,"height":360,"rotate":0}},{"cid":14743527,"page":31,"from":"vupload","part":"day03-7、if结构","duration":919,"vid":"","weblink":"","dimension":{"width":480,"height":360,"rotate":0}},{"cid":14743528,"page":32,"from":"vupload","part":"day03-8、if结构的3个练习wmv","duration":534,"vid":"","weblink":"","dimension":{"width":480,"height":360,"rotate":0}},{"cid":14743529,"page":33,"from":"vupload","part":"day03-9、if-else结构","duration":551,"vid":"","weblink":"","dimension":{"width":480,"height":360,"rotate":0}},{"cid":14743530,"page":34,"from":"vupload","part":"day03-10、if else-if结构","duration":1280,"vid":"","weblink":"","dimension":{"width":480,"height":360,"rotate":0}},{"cid":14743531,"page":35,"from":"vupload","part":"day03-11、四个练习题","duration":1561,"vid":"","weblink":"","dimension":{"width":480,"height":360,"rotate":0}},{"cid":14743532,"page":36,"from":"vupload","part":"day03-12、最后总结","duration":262,"vid":"","weblink":"","dimension":{"width":640,"height":360,"rotate":0}},{"cid":14743533,"page":37,"from":"vupload","part":"day04-1、异常捕获","duration":1457,"vid":"","weblink":"","dimension":{"width":640,"height":360,"rotate":0}},{"cid":14743534,"page":38,"from":"vupload","part":"day04-2、switch-case结构","duration":1388,"vid":"","weblink":"","dimension":{"width":480,"height":360,"rotate":0}},{"cid":14743535,"page":39,"from":"vupload","part":"day04-3、switch-case练习","duration":1185,"vid":"","weblink":"","dimension":{"width":480,"height":360,"rotate":0}},{"cid":14743536,"page":40,"from":"vupload","part":"day04-4、判断年份练习","duration":845,"vid":"","weblink":"","dimension":{"width":480,"height":360,"rotate":0}},{"cid":14743537,"page":41,"from":"vupload","part":"day04-5、while循环","duration":891,"vid":"","weblink":"","dimension":{"width":480,"height":360,"rotate":0}},{"cid":14743538,"page":42,"from":"vupload","part":"day04-6、break的用法和练习","duration":1666,"vid":"","weblink":"","dimension":{"width":480,"height":360,"rotate":0}},{"cid":14743539,"page":43,"from":"vupload","part":"day04-7、while循环的第一个练习","duration":610,"vid":"","weblink":"","dimension":{"width":480,"height":360,"rotate":0}},{"cid":14743540,"page":44,"from":"vupload","part":"day04-8、while循环的练习","duration":2188,"vid":"","weblink":"","dimension":{"width":480,"height":360,"rotate":0}},{"cid":14743541,"page":45,"from":"vupload","part":"day04-9、do-while循环","duration":745,"vid":"","weblink":"","dimension":{"width":480,"height":360,"rotate":0}},{"cid":14743542,"page":46,"from":"vupload","part":"day04-10、最后总结","duration":362,"vid":"","weblink":"","dimension":{"width":640,"height":360,"rotate":0}},{"cid":14743543,"page":47,"from":"vupload","part":"day05-1、复习","duration":751,"vid":"","weblink":"","dimension":{"width":640,"height":360,"rotate":0}},{"cid":14743544,"page":48,"from":"vupload","part":"day05-2、断点调试","duration":929,"vid":"","weblink":"","dimension":{"width":480,"height":360,"rotate":0}},{"cid":14743545,"page":49,"from":"vupload","part":"day05-3、for循环语法","duration":777,"vid":"","weblink":"","dimension":{"width":480,"height":360,"rotate":0}},{"cid":14743597,"page":50,"from":"vupload","part":"day05-4、for循环的练习","duration":746,"vid":"","weblink":"","dimension":{"width":480,"height":360,"rotate":0}},{"cid":14743598,"page":51,"from":"vupload","part":"day05-5、水仙花数","duration":237,"vid":"","weblink":"","dimension":{"width":480,"height":360,"rotate":0}},{"cid":14743599,"page":52,"from":"vupload","part":"day05-6、乘法口诀表","duration":550,"vid":"","weblink":"","dimension":{"width":480,"height":360,"rotate":0}},{"cid":14743600,"page":53,"from":"vupload","part":"day05-7、for循环的嵌套","duration":532,"vid":"","weblink":"","dimension":{"width":480,"height":360,"rotate":0}},{"cid":14743601,"page":54,"from":"vupload","part":"day05-8、三角乘法口诀表","duration":310,"vid":"","weblink":"","dimension":{"width":480,"height":360,"rotate":0}},{"cid":14743602,"page":55,"from":"vupload","part":"day05-9、for循环的练习","duration":177,"vid":"","weblink":"","dimension":{"width":480,"height":360,"rotate":0}},{"cid":14743603,"page":56,"from":"vupload","part":"day05-10、类型转换和方法简介","duration":1130,"vid":"","weblink":"","dimension":{"width":480,"height":360,"rotate":0}},{"cid":14743604,"page":57,"from":"vupload","part":"day05-11、for循环的3个练习","duration":832,"vid":"","weblink":"","dimension":{"width":480,"height":360,"rotate":0}},{"cid":14743605,"page":58,"from":"vupload","part":"day05-12、continue和质数","duration":1001,"vid":"","weblink":"","dimension":{"width":480,"height":360,"rotate":0}},{"cid":14743606,"page":59,"from":"vupload","part":"day05-13、计算质数","duration":846,"vid":"","weblink":"","dimension":{"width":480,"height":360,"rotate":0}},{"cid":14743607,"page":60,"from":"vupload","part":"day05-14、三元表达式","duration":543,"vid":"","weblink":"","dimension":{"width":480,"height":360,"rotate":0}},{"cid":14743608,"page":61,"from":"vupload","part":"day05-15、这个人上辈子是干嘛的","duration":797,"vid":"","weblink":"","dimension":{"width":480,"height":360,"rotate":0}},{"cid":14743609,"page":62,"from":"vupload","part":"day05-16、总结","duration":214,"vid":"","weblink":"","dimension":{"width":640,"height":360,"rotate":0}},{"cid":14743610,"page":63,"from":"vupload","part":"day06-1、复习","duration":690,"vid":"","weblink":"","dimension":{"width":640,"height":360,"rotate":0}},{"cid":14743611,"page":64,"from":"vupload","part":"day06-2、常量","duration":311,"vid":"","weblink":"","dimension":{"width":480,"height":360,"rotate":0}},{"cid":14744461,"page":65,"from":"vupload","part":"day06-3、枚举","duration":1074,"vid":"","weblink":"","dimension":{"width":480,"height":360,"rotate":0}},{"cid":14744462,"page":66,"from":"vupload","part":"day06-4、枚举类型和string以及int类型之间的转换","duration":1783,"vid":"","weblink":"","dimension":{"width":480,"height":360,"rotate":0}},{"cid":14744463,"page":67,"from":"vupload","part":"day06-5结构","duration":1336,"vid":"","weblink":"","dimension":{"width":480,"height":360,"rotate":0}},{"cid":14744464,"page":68,"from":"vupload","part":"day06-6、数组的定义","duration":1512,"vid":"","weblink":"","dimension":{"width":480,"height":360,"rotate":0}},{"cid":14744465,"page":69,"from":"vupload","part":"day06-7、计算数组的最大值、最小值、总和、平均值","duration":1018,"vid":"","weblink":"","dimension":{"width":480,"height":360,"rotate":0}},{"cid":14744466,"page":70,"from":"vupload","part":"day06-8、数组的3个练习","duration":1281,"vid":"","weblink":"","dimension":{"width":480,"height":360,"rotate":0}},{"cid":14744467,"page":71,"from":"vupload","part":"day06-9、冒泡排序","duration":1632,"vid":"","weblink":"","dimension":{"width":480,"height":360,"rotate":0}},{"cid":14744468,"page":72,"from":"vupload","part":"day06-10、方法的简介","duration":2007,"vid":"","weblink":"","dimension":{"width":480,"height":360,"rotate":0}},{"cid":14744469,"page":73,"from":"vupload","part":"day06-11、方法的细节问题","duration":504,"vid":"","weblink":"","dimension":{"width":480,"height":360,"rotate":0}},{"cid":14744470,"page":74,"from":"vupload","part":"day06-12、最后总结","duration":343,"vid":"","weblink":"","dimension":{"width":640,"height":360,"rotate":0}},{"cid":14744471,"page":75,"from":"vupload","part":"day07-1、复习","duration":677,"vid":"","weblink":"","dimension":{"width":640,"height":360,"rotate":0}},{"cid":14744472,"page":76,"from":"vupload","part":"day07-2、方法的调用问题","duration":1546,"vid":"","weblink":"","dimension":{"width":480,"height":360,"rotate":0}},{"cid":14744473,"page":77,"from":"vupload","part":"day07-3、方法练习","duration":2441,"vid":"","weblink":"","dimension":{"width":480,"height":360,"rotate":0}},{"cid":14744474,"page":78,"from":"vupload","part":"day07-4、方法的2个练习","duration":818,"vid":"","weblink":"","dimension":{"width":480,"height":360,"rotate":0}},{"cid":14744475,"page":79,"from":"vupload","part":"day07-5、out参数的使用","duration":2133,"vid":"","weblink":"","dimension":{"width":810,"height":608,"rotate":0}},{"cid":14744476,"page":80,"from":"vupload","part":"day07-6、out参数","duration":295,"vid":"","weblink":"","dimension":{"width":480,"height":360,"rotate":0}},{"cid":14744477,"page":81,"from":"vupload","part":"day07-7、ref参数","duration":595,"vid":"","weblink":"","dimension":{"width":480,"height":360,"rotate":0}},{"cid":14744478,"page":82,"from":"vupload","part":"day07-8、params可变参数","duration":1008,"vid":"","weblink":"","dimension":{"width":480,"height":360,"rotate":0}},{"cid":14744479,"page":83,"from":"vupload","part":"day07-9、方法的重载","duration":1453,"vid":"","weblink":"","dimension":{"width":480,"height":360,"rotate":0}},{"cid":14744480,"page":84,"from":"vupload","part":"day07-10、方法的递归","duration":1113,"vid":"","weblink":"","dimension":{"width":480,"height":360,"rotate":0}},{"cid":14744481,"page":85,"from":"vupload","part":"day07-11、方法的复习","duration":147,"vid":"","weblink":"","dimension":{"width":480,"height":360,"rotate":0}},{"cid":14744482,"page":86,"from":"vupload","part":"day07-12、方法的综合练习","duration":1235,"vid":"","weblink":"","dimension":{"width":1080,"height":608,"rotate":0}},{"cid":14744483,"page":87,"from":"vupload","part":"day08-1、方法的3个练习","duration":1703,"vid":"","weblink":"","dimension":{"width":640,"height":360,"rotate":0}},{"cid":14744484,"page":88,"from":"vupload","part":"day08-2、方法的3个练习","duration":791,"vid":"","weblink":"","dimension":{"width":810,"height":608,"rotate":0}},{"cid":14744485,"page":89,"from":"vupload","part":"day08-3、方法的3个练习","duration":405,"vid":"","weblink":"","dimension":{"width":480,"height":360,"rotate":0}},{"cid":14744486,"page":90,"from":"vupload","part":"day08-4、游戏头","duration":795,"vid":"","weblink":"","dimension":{"width":480,"height":360,"rotate":0}},{"cid":14744487,"page":91,"from":"vupload","part":"day08-5、初始化地图","duration":1476,"vid":"","weblink":"","dimension":{"width":480,"height":360,"rotate":0}},{"cid":14744488,"page":92,"from":"vupload","part":"day08-6、画第一横行","duration":1592,"vid":"","weblink":"","dimension":{"width":810,"height":608,"rotate":0}},{"cid":14744489,"page":93,"from":"vupload","part":"day08-7、画第一竖行","duration":970,"vid":"","weblink":"","dimension":{"width":480,"height":360,"rotate":0}},{"cid":14744490,"page":94,"from":"vupload","part":"day08-8、地图结束","duration":263,"vid":"","weblink":"","dimension":{"width":480,"height":360,"rotate":0}},{"cid":14744491,"page":95,"from":"vupload","part":"day08-9、输入玩家姓名","duration":612,"vid":"","weblink":"","dimension":{"width":480,"height":360,"rotate":0}},{"cid":14744492,"page":96,"from":"vupload","part":"day08-10、玩游戏之前的准备工作","duration":387,"vid":"","weblink":"","dimension":{"width":480,"height":360,"rotate":0}},{"cid":14744493,"page":97,"from":"vupload","part":"day08-11、飞行棋项目结束","duration":3715,"vid":"","weblink":"","dimension":{"width":640,"height":360,"rotate":0}},{"cid":14744494,"page":98,"from":"vupload","part":"day09-1、面向对象概念","duration":3305,"vid":"","weblink":"","dimension":{"width":1080,"height":608,"rotate":0}},{"cid":14744495,"page":99,"from":"vupload","part":"day09-2、类的基本语法","duration":1000,"vid":"","weblink":"","dimension":{"width":480,"height":360,"rotate":0}},{"cid":14744496,"page":100,"from":"vupload","part":"day09-3、属性","duration":3181,"vid":"","weblink":"","dimension":{"width":480,"height":360,"rotate":0}},{"cid":14744497,"page":101,"from":"vupload","part":"day09-4、上午复习","duration":843,"vid":"","weblink":"","dimension":{"width":480,"height":360,"rotate":0}},{"cid":14744498,"page":102,"from":"vupload","part":"day09-5、静态和非静态的区别wmv","duration":2008,"vid":"","weblink":"","dimension":{"width":480,"height":360,"rotate":0}},{"cid":14744499,"page":103,"from":"vupload","part":"day09-6、构造函数","duration":1590,"vid":"","weblink":"","dimension":{"width":480,"height":360,"rotate":0}},{"cid":14744500,"page":104,"from":"vupload","part":"day09-7、this关键字","duration":473,"vid":"","weblink":"","dimension":{"width":480,"height":360,"rotate":0}},{"cid":14744501,"page":105,"from":"vupload","part":"day09-8、析构函数","duration":188,"vid":"","weblink":"","dimension":{"width":480,"height":360,"rotate":0}},{"cid":14744502,"page":106,"from":"vupload","part":"day09-9、最后总结","duration":797,"vid":"","weblink":"","dimension":{"width":640,"height":360,"rotate":0}},{"cid":14744503,"page":107,"from":"vupload","part":"day10-1、复习","duration":1046,"vid":"","weblink":"","dimension":{"width":640,"height":360,"rotate":0}},{"cid":14744504,"page":108,"from":"vupload","part":"day10-2、命名空间","duration":683,"vid":"","weblink":"","dimension":{"width":480,"height":360,"rotate":0}},{"cid":14744505,"page":109,"from":"vupload","part":"day10-3、值类型和引用类型简介","duration":688,"vid":"","weblink":"","dimension":{"width":480,"height":360,"rotate":0}},{"cid":14744506,"page":110,"from":"vupload","part":"day10-4、字符串的不可变性","duration":499,"vid":"","weblink":"","dimension":{"width":480,"height":360,"rotate":0}},{"cid":14744507,"page":111,"from":"vupload","part":"day10-5、字符串的方法(1)","duration":2323,"vid":"","weblink":"","dimension":{"width":480,"height":360,"rotate":0}},{"cid":14744508,"page":112,"from":"vupload","part":"day10-6、字符串的方法(2)","duration":1611,"vid":"","weblink":"","dimension":{"width":480,"height":360,"rotate":0}},{"cid":14744509,"page":113,"from":"vupload","part":"day10-7、复习","duration":752,"vid":"","weblink":"","dimension":{"width":480,"height":360,"rotate":0}},{"cid":14744510,"page":114,"from":"vupload","part":"day10-8、字符串的练习","duration":2008,"vid":"","weblink":"","dimension":{"width":480,"height":360,"rotate":0}},{"cid":14744511,"page":115,"from":"vupload","part":"day10-9、继承","duration":3180,"vid":"","weblink":"","dimension":{"width":480,"height":360,"rotate":0}},{"cid":14744512,"page":116,"from":"vupload","part":"day10-10、继承练习","duration":648,"vid":"","weblink":"","dimension":{"width":480,"height":360,"rotate":0}},{"cid":14744513,"page":117,"from":"vupload","part":"day10-11、关键字的new隐藏父类成员","duration":358,"vid":"","weblink":"","dimension":{"width":480,"height":360,"rotate":0}},{"cid":14744514,"page":118,"from":"vupload","part":"day10-12、最后总结","duration":178,"vid":"","weblink":"","dimension":{"width":640,"height":360,"rotate":0}},{"cid":14744515,"page":119,"from":"vupload","part":"day11-1、复习~1","duration":368,"vid":"","weblink":"","dimension":{"width":640,"height":360,"rotate":0}},{"cid":14744516,"page":120,"from":"vupload","part":"day11-2、里氏转换语法和练习","duration":2384,"vid":"","weblink":"","dimension":{"width":480,"height":360,"rotate":0}},{"cid":14744517,"page":121,"from":"vupload","part":"day11-3、protected访问修饰符","duration":172,"vid":"","weblink":"","dimension":{"width":480,"height":360,"rotate":0}},{"cid":14744518,"page":122,"from":"vupload","part":"day11-4、ArrayList集合的方法","duration":1686,"vid":"","weblink":"","dimension":{"width":480,"height":360,"rotate":0}},{"cid":14744519,"page":123,"from":"vupload","part":"day11-5、集合的长度问题","duration":310,"vid":"","weblink":"","dimension":{"width":480,"height":360,"rotate":0}},{"cid":14744520,"page":124,"from":"vupload","part":"day11-6、集合的两个练习","duration":722,"vid":"","weblink":"","dimension":{"width":480,"height":360,"rotate":0}},{"cid":14746988,"page":125,"from":"vupload","part":"day11-7、Hashtable集合","duration":2635,"vid":"","weblink":"","dimension":{"width":480,"height":360,"rotate":0}},{"cid":14746989,"page":126,"from":"vupload","part":"day11-8、简繁转换","duration":614,"vid":"","weblink":"","dimension":{"width":480,"height":360,"rotate":0}},{"cid":14746990,"page":127,"from":"vupload","part":"day11-9、Path类","duration":546,"vid":"","weblink":"","dimension":{"width":480,"height":360,"rotate":0}},{"cid":14746991,"page":128,"from":"vupload","part":"day11-10、File类的基本操作","duration":401,"vid":"","weblink":"","dimension":{"width":480,"height":360,"rotate":0}},{"cid":14746992,"page":129,"from":"vupload","part":"day11-11、编码简介","duration":343,"vid":"","weblink":"","dimension":{"width":480,"height":360,"rotate":0}},{"cid":14746993,"page":130,"from":"vupload","part":"day11-12、最后小结","duration":357,"vid":"","weblink":"","dimension":{"width":640,"height":360,"rotate":0}}],"subtitle":{"allow_submit":false,"list":[]},"is_season_display":false,"user_garb":{"url_image_ani_cut":""},"honor_reply":{},"like_icon":"","need_jump_bv":false,"disable_show_up_info":false}}