{"code":0,"message":"0","ttl":1,"data":{"bvid":"BV1Db4y1m7Ho","aid":632685046,"videos":104,"tid":231,"tname":"计算机技术","copyright":1,"pic":"http://i0.hdslb.com/bfs/archive/ff64bbd489791c5dea71c1c4567e5c2467af6491.jpg","title":"尚硅谷Python爬虫教程小白零基础速通（含python基础+爬虫案例）","pubdate":1630454415,"ctime":1630454422,"desc":"大家记得一键三连【点赞、投币、收藏】感谢支持~\r\n本教程适合想掌握爬虫技术的学习者，以企业主流版本Python 3.7来讲解，内容包括：Python基础、Urllib、解析（xpath、jsonpath、beautiful）、requests、selenium、Scrapy框架等。针对零基础的同学可以从头学起，有Python基础的同学建议直接从第52集开始学习爬虫部分视频。教程中示例多种网站的爬取，包括设计类网站、招聘类网站、图书类网站、图片素材类网站等，还讲解了验证码的破解和常见的打码平台使用","desc_v2":[{"raw_text":"大家记得一键三连【点赞、投币、收藏】感谢支持~\r\n本教程适合想掌握爬虫技术的学习者，以企业主流版本Python 3.7来讲解，内容包括：Python基础、Urllib、解析（xpath、jsonpath、beautiful）、requests、selenium、Scrapy框架等。针对零基础的同学可以从头学起，有Python基础的同学建议直接从第52集开始学习爬虫部分视频。教程中示例多种网站的爬取，包括设计类网站、招聘类网站、图书类网站、图片素材类网站等，还讲解了验证码的破解和常见的打码平台使用","type":1,"biz_id":0}],"state":0,"duration":80344,"mission_id":94887,"rights":{"bp":0,"elec":0,"download":1,"movie":0,"pay":0,"hd5":0,"no_reprint":1,"autoplay":1,"ugc_pay":0,"is_cooperation":0,"ugc_pay_preview":0,"no_background":0,"clean_mode":0,"is_stein_gate":0,"is_360":0,"no_share":0,"arc_pay":0,"free_watch":0},"owner":{"mid":302417610,"name":"尚硅谷","face":"https://i0.hdslb.com/bfs/face/aabb00d3fa8b1526879ee5fc3875c5f543100aa2.jpg"},"stat":{"aid":632685046,"view":1190010,"danmaku":25452,"reply":1843,"favorite":44972,"coin":13176,"share":8032,"now_rank":0,"his_rank":0,"like":14916,"dislike":0,"evaluation":"","argue_msg":"","vt":0},"dynamic":"","cid":400237926,"dimension":{"width":1364,"height":728,"rotate":0},"premiere":null,"teenage_mode":0,"is_chargeable_season":false,"is_story":false,"is_upower_exclusive":false,"is_upower_play":false,"enable_vt":0,"vt_display":"","no_cache":false,"pages":[{"cid":400237926,"page":1,"from":"vupload","part":"001_尚硅谷_爬虫_课程简介","duration":126,"vid":"","weblink":"","dimension":{"width":1364,"height":728,"rotate":0},"first_frame":"http://i1.hdslb.com/bfs/storyff/n210831a2wi5c88lsre5426buc9abl4i_firsti.jpg"},{"cid":400248404,"page":2,"from":"vupload","part":"002_尚硅谷_爬虫_python环境的安装","duration":1014,"vid":"","weblink":"","dimension":{"width":1364,"height":728,"rotate":0},"first_frame":"http://i0.hdslb.com/bfs/storyff/n210831a2213hvgycg7f9m1bahtbpput_firsti.jpg"},{"cid":400248298,"page":3,"from":"vupload","part":"003_尚硅谷_爬虫_pip指令使用","duration":989,"vid":"","weblink":"","dimension":{"width":1364,"height":728,"rotate":0},"first_frame":"http://i2.hdslb.com/bfs/storyff/n210831a22zp9blhkjvu0y100igdy1tj_firsti.jpg"},{"cid":400248516,"page":4,"from":"vupload","part":"004_尚硅谷_爬虫_终端和文件运行python代码","duration":954,"vid":"","weblink":"","dimension":{"width":1364,"height":728,"rotate":0},"first_frame":"http://i2.hdslb.com/bfs/storyff/n210831a21s4qqdsgznijt2034x3jjk9_firsti.jpg"},{"cid":400249406,"page":5,"from":"vupload","part":"005_尚硅谷_爬虫_pycharm的安装以及基本使用","duration":1052,"vid":"","weblink":"","dimension":{"width":1364,"height":728,"rotate":0},"first_frame":"http://i0.hdslb.com/bfs/storyff/n210831a22h3cqg76g43kf21869wn7al_firsti.jpg"},{"cid":400249897,"page":6,"from":"vupload","part":"006_尚硅谷_爬虫_pycharm结构介绍以及基本配置","duration":613,"vid":"","weblink":"","dimension":{"width":1364,"height":728,"rotate":0},"first_frame":"http://i2.hdslb.com/bfs/storyff/n210831a2639lzjgs7jdn1p395d7d89c_firsti.jpg"},{"cid":400249923,"page":7,"from":"vupload","part":"007_尚硅谷_爬虫_注释","duration":570,"vid":"","weblink":"","dimension":{"width":1364,"height":728,"rotate":0},"first_frame":"http://i1.hdslb.com/bfs/storyff/n210831a21u2o0ogtgdmhd2tbf987v7d_firsti.jpg"},{"cid":400249980,"page":8,"from":"vupload","part":"008_尚硅谷_爬虫_变量的定义","duration":655,"vid":"","weblink":"","dimension":{"width":1364,"height":728,"rotate":0},"first_frame":"http://i2.hdslb.com/bfs/storyff/n210831a21cbltr0ukipnc1qmfzuvb8x_firsti.jpg"},{"cid":400250156,"page":9,"from":"vupload","part":"009_尚硅谷_爬虫_变量类型_number_boolean_string","duration":1501,"vid":"","weblink":"","dimension":{"width":1364,"height":768,"rotate":0},"first_frame":"http://i2.hdslb.com/bfs/storyff/n210831a225c8gpjez2c7xy2m7o70vrt_firsti.jpg"},{"cid":400250052,"page":10,"from":"vupload","part":"010_尚硅谷_爬虫_变量类型_列表_元组_字典","duration":609,"vid":"","weblink":"","dimension":{"width":1364,"height":768,"rotate":0},"first_frame":"http://i0.hdslb.com/bfs/storyff/n210831a23e9cepsq6mj273kswadrafd_firsti.jpg"},{"cid":400250104,"page":11,"from":"vupload","part":"011_尚硅谷_爬虫_查看变量的数据类型","duration":643,"vid":"","weblink":"","dimension":{"width":1364,"height":768,"rotate":0},"first_frame":"http://i2.hdslb.com/bfs/storyff/n210831a2gyej3z5d86dc1695qu4gzfe_firsti.jpg"},{"cid":400250276,"page":12,"from":"vupload","part":"012_尚硅谷_爬虫_变量的命名规范","duration":1079,"vid":"","weblink":"","dimension":{"width":1364,"height":768,"rotate":0},"first_frame":"http://i1.hdslb.com/bfs/storyff/n210831a21so8yi5cwjy092yhfksl2by_firsti.jpg"},{"cid":400250356,"page":13,"from":"vupload","part":"013_尚硅谷_爬虫_类型转换_转换为整型","duration":794,"vid":"","weblink":"","dimension":{"width":1364,"height":768,"rotate":0},"first_frame":"http://i0.hdslb.com/bfs/storyff/n210831a22lcunf7sejpmm19uiwbrbfz_firsti.jpg"},{"cid":400250442,"page":14,"from":"vupload","part":"014_尚硅谷_爬虫_类型转换_转换为浮点数","duration":396,"vid":"","weblink":"","dimension":{"width":1364,"height":768,"rotate":0},"first_frame":"http://i1.hdslb.com/bfs/storyff/n210831a23bjqobawy2abt2uubofc3l9_firsti.jpg"},{"cid":400250530,"page":15,"from":"vupload","part":"015_尚硅谷_爬虫_类型转换_转换为字符串","duration":556,"vid":"","weblink":"","dimension":{"width":1364,"height":768,"rotate":0},"first_frame":"http://i0.hdslb.com/bfs/storyff/n210831a22fqdon4zlzvrd1kqsmdh1j3_firsti.jpg"},{"cid":400250629,"page":16,"from":"vupload","part":"016_尚硅谷_爬虫_类型转换_转换为布尔类型","duration":1519,"vid":"","weblink":"","dimension":{"width":1364,"height":768,"rotate":0},"first_frame":"http://i1.hdslb.com/bfs/storyff/n210831a21kr1wt4aad78y15t3hw48iz_firsti.jpg"},{"cid":400250782,"page":17,"from":"vupload","part":"017_尚硅谷_爬虫_算数运算符","duration":923,"vid":"","weblink":"","dimension":{"width":1364,"height":768,"rotate":0},"first_frame":"http://i2.hdslb.com/bfs/storyff/n210831a2hbae80rr020khzplzc3xqtu_firsti.jpg"},{"cid":400250911,"page":18,"from":"vupload","part":"018_尚硅谷_爬虫_赋值运算符","duration":293,"vid":"","weblink":"","dimension":{"width":1364,"height":768,"rotate":0},"first_frame":"http://i1.hdslb.com/bfs/storyff/n210831a2mj8wzhtja7vv28mknm7v82o_firsti.jpg"},{"cid":400250930,"page":19,"from":"vupload","part":"019_尚硅谷_爬虫_复合赋值运算符","duration":967,"vid":"","weblink":"","dimension":{"width":1364,"height":768,"rotate":0},"first_frame":"http://i2.hdslb.com/bfs/storyff/n210831a2gvffgt61r7le2k9t4wf6vhf_firsti.jpg"},{"cid":400251004,"page":20,"from":"vupload","part":"020_尚硅谷_爬虫_比较运算符","duration":554,"vid":"","weblink":"","dimension":{"width":1364,"height":768,"rotate":0},"first_frame":"http://i1.hdslb.com/bfs/storyff/n210831a21yabchfqircc522jkpw2n99_firsti.jpg"},{"cid":400251099,"page":21,"from":"vupload","part":"021_尚硅谷_爬虫_逻辑运算符","duration":799,"vid":"","weblink":"","dimension":{"width":1364,"height":768,"rotate":0},"first_frame":"http://i1.hdslb.com/bfs/storyff/n210831a2199n384ws8hk930gkdlq3fu_firsti.jpg"},{"cid":400251030,"page":22,"from":"vupload","part":"022_尚硅谷_爬虫_逻辑运算符性能提升","duration":604,"vid":"","weblink":"","dimension":{"width":1364,"height":768,"rotate":0},"first_frame":"http://i0.hdslb.com/bfs/storyff/n210831a299cnwu5gx19b3ume3sfc29u_firsti.jpg"},{"cid":400251186,"page":23,"from":"vupload","part":"023_尚硅谷_爬虫_输出","duration":467,"vid":"","weblink":"","dimension":{"width":1364,"height":768,"rotate":0},"first_frame":"http://i0.hdslb.com/bfs/storyff/n210831a21h72pca6zco6e3hmpw12fa1_firsti.jpg"},{"cid":400251219,"page":24,"from":"vupload","part":"024_尚硅谷_爬虫_输入","duration":413,"vid":"","weblink":"","dimension":{"width":1364,"height":768,"rotate":0},"first_frame":"http://i1.hdslb.com/bfs/storyff/n210831a2jnk5vdhxs5ws3kf2k4bcxuv_firsti.jpg"},{"cid":400251244,"page":25,"from":"vupload","part":"025_尚硅谷_爬虫_流程控制语句_if关键字","duration":573,"vid":"","weblink":"","dimension":{"width":1364,"height":768,"rotate":0},"first_frame":"http://i2.hdslb.com/bfs/storyff/n210831a22uuqy2mc95wy33p1iswb3ve_firsti.jpg"},{"cid":400251295,"page":26,"from":"vupload","part":"026_尚硅谷_爬虫_流程控制语句_if案例练习","duration":406,"vid":"","weblink":"","dimension":{"width":1364,"height":768,"rotate":0},"first_frame":"http://i0.hdslb.com/bfs/storyff/n210831a22n7xf74fkh3st1dzttzkofy_firsti.jpg"},{"cid":400251340,"page":27,"from":"vupload","part":"027_尚硅谷_爬虫_流程控制语句_ifelse关键字","duration":289,"vid":"","weblink":"","dimension":{"width":1364,"height":768,"rotate":0},"first_frame":"http://i2.hdslb.com/bfs/storyff/n210831a23948jaa95v3j91id5cucciy_firsti.jpg"},{"cid":400251370,"page":28,"from":"vupload","part":"028_尚硅谷_爬虫_流程控制语句_ifelse案例练习","duration":279,"vid":"","weblink":"","dimension":{"width":1364,"height":768,"rotate":0},"first_frame":"http://i0.hdslb.com/bfs/storyff/n210831a2bfsy8ar4b1cf3c3a4l2cycc_firsti.jpg"},{"cid":400251392,"page":29,"from":"vupload","part":"029_尚硅谷_爬虫_流程控制语句_elif","duration":738,"vid":"","weblink":"","dimension":{"width":1364,"height":768,"rotate":0},"first_frame":"http://i0.hdslb.com/bfs/storyff/n210831a21ztszfkgf0h793f3cnt0xed_firsti.jpg"},{"cid":400251461,"page":30,"from":"vupload","part":"030_尚硅谷_爬虫_流程控制语句_for循环","duration":1209,"vid":"","weblink":"","dimension":{"width":1364,"height":768,"rotate":0},"first_frame":"http://i1.hdslb.com/bfs/storyff/n210831a22pcnf55vwituv3l952zwlr7_firsti.jpg"},{"cid":400251561,"page":31,"from":"vupload","part":"031_尚硅谷_爬虫_字符串高级","duration":977,"vid":"","weblink":"","dimension":{"width":1364,"height":768,"rotate":0},"first_frame":"http://i1.hdslb.com/bfs/storyff/n210831a23ihpjr64cm8y2iwtniveq1j_firsti.jpg"},{"cid":400251673,"page":32,"from":"vupload","part":"032_尚硅谷_爬虫_列表高级_添加","duration":688,"vid":"","weblink":"","dimension":{"width":1364,"height":768,"rotate":0},"first_frame":"http://i0.hdslb.com/bfs/storyff/n210831a22dgwfxqf3eif7gcfggn9i0o_firsti.jpg"},{"cid":400251656,"page":33,"from":"vupload","part":"033_尚硅谷_爬虫_列表高级_修改","duration":186,"vid":"","weblink":"","dimension":{"width":1364,"height":768,"rotate":0},"first_frame":"http://i0.hdslb.com/bfs/storyff/n210831a2cq9q529dz32e1cmnma8cqkt_firsti.jpg"},{"cid":400251726,"page":34,"from":"vupload","part":"034_尚硅谷_爬虫_列表高级_查询","duration":473,"vid":"","weblink":"","dimension":{"width":1364,"height":768,"rotate":0},"first_frame":"http://i0.hdslb.com/bfs/storyff/n210831a22bvh4jkbv57xw1sq9xxwl0j_firsti.jpg"},{"cid":400251766,"page":35,"from":"vupload","part":"035_尚硅谷_爬虫_列表高级_删除","duration":521,"vid":"","weblink":"","dimension":{"width":1680,"height":1000,"rotate":0},"first_frame":"http://i0.hdslb.com/bfs/storyff/n210831a233poaop1uvzvo2erxam8j21_firsti.jpg"},{"cid":400251825,"page":36,"from":"vupload","part":"036_尚硅谷_爬虫_元组高级","duration":461,"vid":"","weblink":"","dimension":{"width":1680,"height":1000,"rotate":0},"first_frame":"http://i0.hdslb.com/bfs/storyff/n210831a23qgprhbdjf2rl3fxx57nrez_firsti.jpg"},{"cid":400257538,"page":37,"from":"vupload","part":"037_尚硅谷_爬虫_切片","duration":553,"vid":"","weblink":"","dimension":{"width":1680,"height":1000,"rotate":0},"first_frame":"http://i0.hdslb.com/bfs/storyff/n210831a21pojqk2qita5n3eo86smwhm_firsti.jpg"},{"cid":400257641,"page":38,"from":"vupload","part":"038_尚硅谷_爬虫_字典的高级_查询","duration":475,"vid":"","weblink":"","dimension":{"width":1680,"height":998,"rotate":0},"first_frame":"http://i0.hdslb.com/bfs/storyff/n210831a21la6em4llbt5x25b2iwbsaz_firsti.jpg"},{"cid":400257776,"page":39,"from":"vupload","part":"039_尚硅谷_爬虫_字典的高级_修改","duration":210,"vid":"","weblink":"","dimension":{"width":1680,"height":998,"rotate":0},"first_frame":"http://i1.hdslb.com/bfs/storyff/n210831a21x3lek8nra1mx1jm0on2w7g_firsti.jpg"},{"cid":400257724,"page":40,"from":"vupload","part":"040_尚硅谷_爬虫_字典的高级_添加","duration":242,"vid":"","weblink":"","dimension":{"width":1680,"height":998,"rotate":0},"first_frame":"http://i2.hdslb.com/bfs/storyff/n210831a21kgdwg78allhw2uoqy0z7gf_firsti.jpg"},{"cid":400257811,"page":41,"from":"vupload","part":"041_尚硅谷_爬虫_字典的高级_删除","duration":395,"vid":"","weblink":"","dimension":{"width":1680,"height":998,"rotate":0},"first_frame":"http://i0.hdslb.com/bfs/storyff/n210831a21cq0qn3j2ixs233gpmgi5pl_firsti.jpg"},{"cid":400257896,"page":42,"from":"vupload","part":"042_尚硅谷_爬虫_字典的高级_遍历","duration":580,"vid":"","weblink":"","dimension":{"width":1680,"height":998,"rotate":0},"first_frame":"http://i2.hdslb.com/bfs/storyff/n210831a234xtjvhe7gdir34c8sidg5c_firsti.jpg"},{"cid":400257961,"page":43,"from":"vupload","part":"043_尚硅谷_爬虫_函数_函数的定义和调用","duration":478,"vid":"","weblink":"","dimension":{"width":1680,"height":998,"rotate":0},"first_frame":"http://i0.hdslb.com/bfs/storyff/n210831a21ietps3ilqxtzoh5j2mjap7_firsti.jpg"},{"cid":400258029,"page":44,"from":"vupload","part":"044_尚硅谷_爬虫_函数_函数的参数","duration":618,"vid":"","weblink":"","dimension":{"width":1680,"height":998,"rotate":0},"first_frame":"http://i0.hdslb.com/bfs/storyff/n210831a2dyy455o12rtf2wyogzttluo_firsti.jpg"},{"cid":400258116,"page":45,"from":"vupload","part":"045_尚硅谷_爬虫_函数_函数的返回值","duration":525,"vid":"","weblink":"","dimension":{"width":1680,"height":998,"rotate":0},"first_frame":"http://i2.hdslb.com/bfs/storyff/n210831a2skoe648bgbcd34c9ay95863_firsti.jpg"},{"cid":400258177,"page":46,"from":"vupload","part":"046_尚硅谷_爬虫_函数_函数的局部变量和全局变量","duration":378,"vid":"","weblink":"","dimension":{"width":1680,"height":998,"rotate":0},"first_frame":"http://i1.hdslb.com/bfs/storyff/n210831a2owlq0qpbbwhh3luzu8yniq6_firsti.jpg"},{"cid":400258234,"page":47,"from":"vupload","part":"047_尚硅谷_爬虫_文件_文件的打开和关闭","duration":797,"vid":"","weblink":"","dimension":{"width":1680,"height":998,"rotate":0},"first_frame":"http://i2.hdslb.com/bfs/storyff/n210831a22az1v5exu1czf1bw7qxwbvg_firsti.jpg"},{"cid":400258356,"page":48,"from":"vupload","part":"048_尚硅谷_爬虫_文件_文件的读写","duration":586,"vid":"","weblink":"","dimension":{"width":1680,"height":998,"rotate":0},"first_frame":"http://i0.hdslb.com/bfs/storyff/n210831a23afzas1xpigzvvn7sti187o_firsti.jpg"},{"cid":400258479,"page":49,"from":"vupload","part":"049_尚硅谷_爬虫_文件_文件的序列化和反序列化","duration":1285,"vid":"","weblink":"","dimension":{"width":1680,"height":998,"rotate":0},"first_frame":"http://i2.hdslb.com/bfs/storyff/n210831a21uop9sv5dnh6i1o88g0y5ra_firsti.jpg"},{"cid":400258442,"page":50,"from":"vupload","part":"050_尚硅谷_爬虫_异常","duration":284,"vid":"","weblink":"","dimension":{"width":1680,"height":998,"rotate":0},"first_frame":"http://i1.hdslb.com/bfs/storyff/n210831a23lf8598azf5dj1grevmvmek_firsti.jpg"},{"cid":400258926,"page":51,"from":"vupload","part":"051_尚硅谷_爬虫_页面结构的介绍","duration":843,"vid":"","weblink":"","dimension":{"width":1680,"height":998,"rotate":0},"first_frame":"http://i1.hdslb.com/bfs/storyff/n210831a2elwwjh0ol9rzhim2m1cdjui_firsti.jpg"},{"cid":400258692,"page":52,"from":"vupload","part":"052_尚硅谷_爬虫_爬虫相关概念介绍","duration":1361,"vid":"","weblink":"","dimension":{"width":1680,"height":998,"rotate":0},"first_frame":"http://i2.hdslb.com/bfs/storyff/n210831a21soais9nsluj61dgeg0ha73_firsti.jpg"},{"cid":400259082,"page":53,"from":"vupload","part":"053_尚硅谷_爬虫_urllib_基本使用","duration":904,"vid":"","weblink":"","dimension":{"width":1680,"height":998,"rotate":0},"first_frame":"http://i2.hdslb.com/bfs/storyff/n210831a24v3sqdqjij6q2856dwq51hr_firsti.jpg"},{"cid":400259204,"page":54,"from":"vupload","part":"054_尚硅谷_爬虫_urllib_1个类型和6个方法","duration":657,"vid":"","weblink":"","dimension":{"width":1680,"height":998,"rotate":0},"first_frame":"http://i0.hdslb.com/bfs/storyff/n210831a238wsijt9c99wc3ckx6f36ld_firsti.jpg"},{"cid":400259276,"page":55,"from":"vupload","part":"055_尚硅谷_爬虫_urllib_下载","duration":585,"vid":"","weblink":"","dimension":{"width":1680,"height":998,"rotate":0},"first_frame":"http://i0.hdslb.com/bfs/storyff/n210831a223ye9ldql1qvr26j1cdx038_firsti.jpg"},{"cid":400259435,"page":56,"from":"vupload","part":"056_尚硅谷_爬虫_urllib_请求对象的定制","duration":989,"vid":"","weblink":"","dimension":{"width":1680,"height":998,"rotate":0},"first_frame":"http://i0.hdslb.com/bfs/storyff/n210831a212a46mlxeetva1gzg2zxd9a_firsti.jpg"},{"cid":400259653,"page":57,"from":"vupload","part":"057_尚硅谷_爬虫_urllib_get请求的quote方法","duration":990,"vid":"","weblink":"","dimension":{"width":1680,"height":998,"rotate":0},"first_frame":"http://i2.hdslb.com/bfs/storyff/n210831a2kxps17snsm333g2f74iy653_firsti.jpg"},{"cid":400259860,"page":58,"from":"vupload","part":"058_尚硅谷_爬虫_urllib_get请求的urlencode方法","duration":723,"vid":"","weblink":"","dimension":{"width":1680,"height":998,"rotate":0},"first_frame":"http://i1.hdslb.com/bfs/storyff/n210831a2g3h7gijb2psw22hppyhodz4_firsti.jpg"},{"cid":400259968,"page":59,"from":"vupload","part":"059_尚硅谷_爬虫_urllib_post请求百度翻译","duration":982,"vid":"","weblink":"","dimension":{"width":1680,"height":998,"rotate":0},"first_frame":"http://i1.hdslb.com/bfs/storyff/n210831a23a3k8cymli4ly1dmekp02ax_firsti.jpg"},{"cid":400260152,"page":60,"from":"vupload","part":"060_尚硅谷_爬虫_urllib_post请求百度翻译之详细翻译","duration":755,"vid":"","weblink":"","dimension":{"width":1680,"height":998,"rotate":0},"first_frame":"http://i0.hdslb.com/bfs/storyff/n210831a21p48s9ragb12m3vu1nk9di4_firsti.jpg"},{"cid":400260307,"page":61,"from":"vupload","part":"061_尚硅谷_爬虫_urllib_ajax的get请求豆瓣电影第一页","duration":785,"vid":"","weblink":"","dimension":{"width":1680,"height":998,"rotate":0},"first_frame":"http://i0.hdslb.com/bfs/storyff/n210831a230wldmuns1cw03eqt89wwjg_firsti.jpg"},{"cid":400260466,"page":62,"from":"vupload","part":"062_尚硅谷_爬虫_urllib_ajax的get请求豆瓣电影前10页","duration":1652,"vid":"","weblink":"","dimension":{"width":1680,"height":998,"rotate":0},"first_frame":"http://i0.hdslb.com/bfs/storyff/n210831a23tavgcm1qlnuv36pb522pby_firsti.jpg"},{"cid":400260809,"page":63,"from":"vupload","part":"063_尚硅谷_爬虫_urllib_ajax的post请求肯德基官网","duration":843,"vid":"","weblink":"","dimension":{"width":1680,"height":998,"rotate":0},"first_frame":"http://i1.hdslb.com/bfs/storyff/n210831a21v134alg0i4bjghi3qtfdrj_firsti.jpg"},{"cid":400260976,"page":64,"from":"vupload","part":"064_尚硅谷_爬虫_urllib_异常","duration":492,"vid":"","weblink":"","dimension":{"width":1680,"height":998,"rotate":0},"first_frame":"http://i1.hdslb.com/bfs/storyff/n210831a2155q6cq3ywqz6p41l1ffrld_firsti.jpg"},{"cid":400261078,"page":65,"from":"vupload","part":"065_尚硅谷_爬虫_urllib_微博的cookie登陆","duration":922,"vid":"","weblink":"","dimension":{"width":1680,"height":998,"rotate":0},"first_frame":"http://i0.hdslb.com/bfs/storyff/n210831a2c1nyjka180ru3ibagr4dc1o_firsti.jpg"},{"cid":400261276,"page":66,"from":"vupload","part":"066_尚硅谷_爬虫_urllib_handler处理器的基本使用","duration":493,"vid":"","weblink":"","dimension":{"width":1680,"height":998,"rotate":0},"first_frame":"http://i0.hdslb.com/bfs/storyff/n210831a22cr3ygdub0ync2jnz55cphh_firsti.jpg"},{"cid":400261342,"page":67,"from":"vupload","part":"067_尚硅谷_爬虫_urllib_代理","duration":800,"vid":"","weblink":"","dimension":{"width":1680,"height":998,"rotate":0},"first_frame":"http://i0.hdslb.com/bfs/storyff/n210831a237r777ygp4mtq3ni34tdqr5_firsti.jpg"},{"cid":400261495,"page":68,"from":"vupload","part":"068_尚硅谷_爬虫_urllib_代理池","duration":372,"vid":"","weblink":"","dimension":{"width":1680,"height":998,"rotate":0},"first_frame":"http://i2.hdslb.com/bfs/storyff/n210831a2t5iwd2xjft9ag1zpnu3e9o0_firsti.jpg"},{"cid":400261575,"page":69,"from":"vupload","part":"069_尚硅谷_爬虫_解析_xpath插件的安装","duration":528,"vid":"","weblink":"","dimension":{"width":1680,"height":998,"rotate":0},"first_frame":"http://i1.hdslb.com/bfs/storyff/n210831a21ab8a5r2orba834o4v1nc8m_firsti.jpg"},{"cid":400261658,"page":70,"from":"vupload","part":"070_尚硅谷_爬虫_解析_xpath的基本使用","duration":1915,"vid":"","weblink":"","dimension":{"width":1680,"height":998,"rotate":0},"first_frame":"http://i1.hdslb.com/bfs/storyff/n210831a2157m11oyr31k38ny8pomf79_firsti.jpg"},{"cid":400261986,"page":71,"from":"vupload","part":"071_尚硅谷_爬虫_解析_获取百度网站的百度一下","duration":587,"vid":"","weblink":"","dimension":{"width":1680,"height":998,"rotate":0},"first_frame":"http://i1.hdslb.com/bfs/storyff/n210831a2n5i17ydjoz1w1pdganwr3nh_firsti.jpg"},{"cid":400262109,"page":72,"from":"vupload","part":"072_尚硅谷_爬虫_解析_站长素材","duration":1771,"vid":"","weblink":"","dimension":{"width":1680,"height":998,"rotate":0},"first_frame":"http://i1.hdslb.com/bfs/storyff/n210831a2msy1fz4uy3q9wg3onq8ksj9_firsti.jpg"},{"cid":400263461,"page":73,"from":"vupload","part":"073_尚硅谷_爬虫_解析_jsonpath","duration":1238,"vid":"","weblink":"","dimension":{"width":1680,"height":998,"rotate":0},"first_frame":"http://i0.hdslb.com/bfs/storyff/n210831a2216q8urrq27lh2s63kfl3ag_firsti.jpg"},{"cid":400263722,"page":74,"from":"vupload","part":"074_尚硅谷_爬虫_解析_jsonpath解析淘票票","duration":653,"vid":"","weblink":"","dimension":{"width":1680,"height":998,"rotate":0},"first_frame":"http://i2.hdslb.com/bfs/storyff/n210831a2yjvfrtnmiq1w2ushh8zbnp8_firsti.jpg"},{"cid":400264067,"page":75,"from":"vupload","part":"075_尚硅谷_爬虫_解析_bs4的基本使用","duration":2433,"vid":"","weblink":"","dimension":{"width":1680,"height":998,"rotate":0},"first_frame":"http://i2.hdslb.com/bfs/storyff/n210831a213uvclp6w96q9ckm02joykd_firsti.jpg"},{"cid":400263915,"page":76,"from":"vupload","part":"076_尚硅谷_爬虫_解析_bs4爬取星巴克数据","duration":739,"vid":"","weblink":"","dimension":{"width":1680,"height":998,"rotate":0},"first_frame":"http://i1.hdslb.com/bfs/storyff/n210831a21rqngnm0fpn0mophlqlpo4a_firsti.jpg"},{"cid":400265602,"page":77,"from":"vupload","part":"077_尚硅谷_爬虫_selenium_为什么要学习selenium","duration":390,"vid":"","weblink":"","dimension":{"width":1680,"height":998,"rotate":0},"first_frame":"http://i0.hdslb.com/bfs/storyff/n210831a224ri9gcphgr231vrnzd65uw_firsti.jpg"},{"cid":400265698,"page":78,"from":"vupload","part":"078_尚硅谷_爬虫_selenium_基本使用","duration":602,"vid":"","weblink":"","dimension":{"width":1680,"height":998,"rotate":0},"first_frame":"http://i2.hdslb.com/bfs/storyff/n210831a233rgdlr9at3kg2sjwbpz6gv_firsti.jpg"},{"cid":400265831,"page":79,"from":"vupload","part":"079_尚硅谷_爬虫_selenium_元素定位","duration":721,"vid":"","weblink":"","dimension":{"width":1680,"height":998,"rotate":0},"first_frame":"http://i2.hdslb.com/bfs/storyff/n210831a21uj6jeew3tc5k27a1docjtb_firsti.jpg"},{"cid":400265964,"page":80,"from":"vupload","part":"080_尚硅谷_爬虫_selenium_元素信息","duration":372,"vid":"","weblink":"","dimension":{"width":1680,"height":998,"rotate":0},"first_frame":"http://i2.hdslb.com/bfs/storyff/n210831a2mp3lkvgbh34538hlzpwby34_firsti.jpg"},{"cid":400266019,"page":81,"from":"vupload","part":"081_尚硅谷_爬虫_selenium_交互","duration":745,"vid":"","weblink":"","dimension":{"width":1680,"height":998,"rotate":0},"first_frame":"http://i1.hdslb.com/bfs/storyff/n210831a2cij79sjyd9j78vxrqjmqiq1_firsti.jpg"},{"cid":400266515,"page":82,"from":"vupload","part":"082_尚硅谷_爬虫_selenium_phantomjs的基本使用","duration":439,"vid":"","weblink":"","dimension":{"width":1680,"height":998,"rotate":0},"first_frame":"http://i0.hdslb.com/bfs/storyff/n210831a2hxgq1g5wfv1618kgo8u3fsu_firsti.jpg"},{"cid":400258114,"page":83,"from":"vupload","part":"083_尚硅谷_爬虫_selenium_handless","duration":448,"vid":"","weblink":"","dimension":{"width":1680,"height":998,"rotate":0},"first_frame":"http://i1.hdslb.com/bfs/storyff/n210831a22x4nmraoqeyk2qfandcflfi_firsti.jpg"},{"cid":400266639,"page":84,"from":"vupload","part":"084_尚硅谷_爬虫_requests_基本使用","duration":681,"vid":"","weblink":"","dimension":{"width":1680,"height":998,"rotate":0},"first_frame":"http://i2.hdslb.com/bfs/storyff/n210831a23jp634w721ail2ug9x5vxnl_firsti.jpg"},{"cid":400266833,"page":85,"from":"vupload","part":"085_尚硅谷_爬虫_requests_get请求","duration":750,"vid":"","weblink":"","dimension":{"width":1680,"height":998,"rotate":0},"first_frame":"http://i1.hdslb.com/bfs/storyff/n210831a217dqgllcg4e9reuck7vz0ed_firsti.jpg"},{"cid":400266759,"page":86,"from":"vupload","part":"086_尚硅谷_爬虫_requests_post请求","duration":477,"vid":"","weblink":"","dimension":{"width":1680,"height":998,"rotate":0},"first_frame":"http://i0.hdslb.com/bfs/storyff/n210831a21q2mfv156epzm31q3kbyc9r_firsti.jpg"},{"cid":400266962,"page":87,"from":"vupload","part":"087_尚硅谷_爬虫_requests_代理","duration":364,"vid":"","weblink":"","dimension":{"width":1680,"height":998,"rotate":0},"first_frame":"http://i1.hdslb.com/bfs/storyff/n210831a2bkwavrahz9gw1hash06o54j_firsti.jpg"},{"cid":400267158,"page":88,"from":"vupload","part":"088_尚硅谷_爬虫_requests_cookie登陆古诗文网","duration":2445,"vid":"","weblink":"","dimension":{"width":1680,"height":998,"rotate":0},"first_frame":"http://i0.hdslb.com/bfs/storyff/n210831a21yn8s61dslvhr27meg6mu39_firsti.jpg"},{"cid":400267648,"page":89,"from":"vupload","part":"089_尚硅谷_爬虫_requests_超级鹰打码平台的使用","duration":453,"vid":"","weblink":"","dimension":{"width":1680,"height":998,"rotate":0},"first_frame":"http://i0.hdslb.com/bfs/storyff/n210831a21x4uvvhza9ofced5plrguc4_firsti.jpg"},{"cid":400267744,"page":90,"from":"vupload","part":"090_尚硅谷_爬虫_scrapy_安装","duration":1089,"vid":"","weblink":"","dimension":{"width":1680,"height":998,"rotate":0},"first_frame":"http://i0.hdslb.com/bfs/storyff/n210831a22ingmhq0vfzqn1dchxbib1c_firsti.jpg"},{"cid":400267990,"page":91,"from":"vupload","part":"091_尚硅谷_爬虫_scrapy_基本使用","duration":1200,"vid":"","weblink":"","dimension":{"width":1680,"height":998,"rotate":0},"first_frame":"http://i1.hdslb.com/bfs/storyff/n210831a2xt4zuluaqp6c30sz9m1q28c_firsti.jpg"},{"cid":400268212,"page":92,"from":"vupload","part":"092_尚硅谷_爬虫_scrapy_58同城项目结构和基本方法","duration":1064,"vid":"","weblink":"","dimension":{"width":1680,"height":998,"rotate":0},"first_frame":"http://i1.hdslb.com/bfs/storyff/n210831a221uaste5wocr37ofp2jx81s_firsti.jpg"},{"cid":400268571,"page":93,"from":"vupload","part":"093_尚硅谷_爬虫_scrapy_汽车之家scrapy工作原理","duration":1246,"vid":"","weblink":"","dimension":{"width":1680,"height":998,"rotate":0},"first_frame":"http://i2.hdslb.com/bfs/storyff/n210831a21xqgngpytmyvf2mp3w6go31_firsti.jpg"},{"cid":400268817,"page":94,"from":"vupload","part":"094_尚硅谷_爬虫_scrapy_scrapyshell","duration":717,"vid":"","weblink":"","dimension":{"width":1680,"height":998,"rotate":0},"first_frame":"http://i2.hdslb.com/bfs/storyff/n210831a22pr1z7si9iwlfspogkn9x82_firsti.jpg"},{"cid":400268954,"page":95,"from":"vupload","part":"095_尚硅谷_爬虫_scrapy_当当网爬取数据","duration":1452,"vid":"","weblink":"","dimension":{"width":1680,"height":998,"rotate":0},"first_frame":"http://i0.hdslb.com/bfs/storyff/n210831a2bixwbk7htkm226g3e2hah9a_firsti.jpg"},{"cid":400269389,"page":96,"from":"vupload","part":"096_尚硅谷_爬虫_scrapy_当当网管道封装","duration":935,"vid":"","weblink":"","dimension":{"width":1680,"height":998,"rotate":0},"first_frame":"http://i1.hdslb.com/bfs/storyff/n210831a2km3koif1dss02ze074yd8wb_firsti.jpg"},{"cid":400309932,"page":97,"from":"vupload","part":"097_尚硅谷_爬虫_scrapy_当当网开启多条管道下载","duration":367,"vid":"","weblink":"","dimension":{"width":1680,"height":998,"rotate":0},"first_frame":"http://i0.hdslb.com/bfs/storyff/n210831a2355eg7vo4nnyr3pkbw7b3a7_firsti.jpg"},{"cid":400310037,"page":98,"from":"vupload","part":"098_尚硅谷_爬虫_scrapy_当当网多页下载","duration":686,"vid":"","weblink":"","dimension":{"width":1680,"height":998,"rotate":0},"first_frame":"http://i2.hdslb.com/bfs/storyff/n210831a225fsdmvubcxug2asdxw29z5_firsti.jpg"},{"cid":400310370,"page":99,"from":"vupload","part":"099_尚硅谷_爬虫_scrapy_电影天堂多页数据下载","duration":1441,"vid":"","weblink":"","dimension":{"width":1680,"height":998,"rotate":0},"first_frame":"http://i2.hdslb.com/bfs/storyff/n210831a22qu2m6am2sl6v35ey9mg51j_firsti.jpg"},{"cid":400311020,"page":100,"from":"vupload","part":"100_尚硅谷_爬虫_scrapy_链接提取器的使用","duration":678,"vid":"","weblink":"","dimension":{"width":1680,"height":998,"rotate":0},"first_frame":"http://i1.hdslb.com/bfs/storyff/n210831a2dnvsxablm6m42voej9sik7n_firsti.jpg"},{"cid":400311189,"page":101,"from":"vupload","part":"101_尚硅谷_爬虫_scrapy_crawlspider读书网","duration":1138,"vid":"","weblink":"","dimension":{"width":1680,"height":998,"rotate":0},"first_frame":"http://i0.hdslb.com/bfs/storyff/n210831a210s3f4xcq969f3gixbaxoyn_firsti.jpg"},{"cid":400312068,"page":102,"from":"vupload","part":"102_尚硅谷_爬虫_scrapy_读书网数据入库和链接跟进","duration":1295,"vid":"","weblink":"","dimension":{"width":1680,"height":998,"rotate":0},"first_frame":"http://i0.hdslb.com/bfs/storyff/n210831a23ks02691n5lei3qpgmhhk2v_firsti.jpg"},{"cid":400312368,"page":103,"from":"vupload","part":"103_尚硅谷_爬虫_scrapy_日志信息以及日志级别","duration":360,"vid":"","weblink":"","dimension":{"width":1680,"height":998,"rotate":0},"first_frame":"http://i0.hdslb.com/bfs/storyff/n210831a23g0u44s34898g26wkmx83n9_firsti.jpg"},{"cid":400312419,"page":104,"from":"vupload","part":"104_尚硅谷_爬虫_scrapy_百度翻译post请求","duration":481,"vid":"","weblink":"","dimension":{"width":1680,"height":998,"rotate":0},"first_frame":"http://i0.hdslb.com/bfs/storyff/n210831a218h3xpr69ec3336no1s5sbe_firsti.jpg"}],"subtitle":{"allow_submit":false,"list":[]},"is_season_display":false,"user_garb":{"url_image_ani_cut":""},"honor_reply":{},"like_icon":"","need_jump_bv":false,"disable_show_up_info":false}}