{"code":0,"message":"0","ttl":1,"data":{"bvid":"BV1Ds411E76Y","aid":27212529,"videos":90,"tid":208,"tname":"校园学习","copyright":2,"pic":"http://i1.hdslb.com/bfs/archive/e336a1c33d961c539f1f94bcf75e387cf7b4a977.png","title":"尚硅谷MyBatisPlus教程(mybatis-plus框架精讲)","pubdate":1531981707,"ctime":1531981707,"desc":"2022新版MyBatis-Plus：BV12R4y157Be\n\nMyBatis ：BV1VP4y1c7j7（全面更新、细致讲解）\n\nMyBatis-Plus是一款非常强大的MyBatis增强工具包,只做增强不做改变.在不用编写任何SQL语句的情况下即可以极其方便的实现单一、批量、分页等操作。本套教程基于MyBatis-Plus新2.3版本。","desc_v2":[{"raw_text":"2022新版MyBatis-Plus：BV12R4y157Be\n\nMyBatis ：BV1VP4y1c7j7（全面更新、细致讲解）\n\nMyBatis-Plus是一款非常强大的MyBatis增强工具包,只做增强不做改变.在不用编写任何SQL语句的情况下即可以极其方便的实现单一、批量、分页等操作。本套教程基于MyBatis-Plus新2.3版本。","type":1,"biz_id":0}],"state":0,"duration":26561,"rights":{"bp":0,"elec":0,"download":1,"movie":0,"pay":0,"hd5":0,"no_reprint":0,"autoplay":1,"ugc_pay":0,"is_cooperation":0,"ugc_pay_preview":0,"no_background":0,"clean_mode":0,"is_stein_gate":0,"is_360":0,"no_share":0,"arc_pay":0,"free_watch":0},"owner":{"mid":302417610,"name":"尚硅谷","face":"https://i0.hdslb.com/bfs/face/aabb00d3fa8b1526879ee5fc3875c5f543100aa2.jpg"},"stat":{"aid":27212529,"view":236055,"danmaku":1978,"reply":158,"favorite":8462,"coin":804,"share":487,"now_rank":0,"his_rank":0,"like":1648,"dislike":0,"evaluation":"","argue_msg":"","vt":0},"dynamic":"","cid":268035081,"dimension":{"width":1366,"height":768,"rotate":0},"premiere":null,"teenage_mode":0,"is_chargeable_season":false,"is_story":false,"is_upower_exclusive":false,"is_upower_play":false,"enable_vt":0,"vt_display":"","no_cache":false,"pages":[{"cid":268035081,"page":1,"from":"vupload","part":"1_尚硅谷_简介","duration":213,"vid":"","weblink":"","dimension":{"width":1366,"height":768,"rotate":0}},{"cid":46903535,"page":2,"from":"vupload","part":"2_尚硅谷_代码及文档地址","duration":392,"vid":"","weblink":"","dimension":{"width":1366,"height":768,"rotate":0}},{"cid":46903566,"page":3,"from":"vupload","part":"3_尚硅谷_前置知识","duration":88,"vid":"","weblink":"","dimension":{"width":1366,"height":768,"rotate":0}},{"cid":46903603,"page":4,"from":"vupload","part":"4_尚硅谷_集成MP_准备测试表","duration":118,"vid":"","weblink":"","dimension":{"width":1366,"height":768,"rotate":0}},{"cid":46903610,"page":5,"from":"vupload","part":"5_尚硅谷_集成MP_准备JavaBean类","duration":390,"vid":"","weblink":"","dimension":{"width":1366,"height":768,"rotate":0}},{"cid":46903626,"page":6,"from":"vupload","part":"6_尚硅谷_集成MP_加入Maven依赖信息","duration":244,"vid":"","weblink":"","dimension":{"width":1366,"height":768,"rotate":0}},{"cid":46903680,"page":7,"from":"vupload","part":"7_尚硅谷_集成MP_搭建Mybatis与Spring的环境","duration":262,"vid":"","weblink":"","dimension":{"width":1366,"height":768,"rotate":0}},{"cid":46903710,"page":8,"from":"vupload","part":"8_尚硅谷_集成MP_环境测试","duration":241,"vid":"","weblink":"","dimension":{"width":1366,"height":768,"rotate":0}},{"cid":46903738,"page":9,"from":"vupload","part":"9_尚硅谷_集成MP_将MybatisPlus集成进来","duration":154,"vid":"","weblink":"","dimension":{"width":1366,"height":768,"rotate":0}},{"cid":46903758,"page":10,"from":"vupload","part":"10_尚硅谷_通用CRUD_创建具体的Mapper接口","duration":453,"vid":"","weblink":"","dimension":{"width":1366,"height":768,"rotate":0}},{"cid":46903774,"page":11,"from":"vupload","part":"11_尚硅谷_通用CRUD_BaseMapper接口介绍","duration":187,"vid":"","weblink":"","dimension":{"width":1366,"height":768,"rotate":0}},{"cid":46903810,"page":12,"from":"vupload","part":"12_尚硅谷_通用CRUD_insert方法","duration":265,"vid":"","weblink":"","dimension":{"width":1366,"height":768,"rotate":0}},{"cid":46903820,"page":13,"from":"vupload","part":"13_尚硅谷_通用CRUD_@TableId注解","duration":436,"vid":"","weblink":"","dimension":{"width":1366,"height":768,"rotate":0}},{"cid":46903846,"page":14,"from":"vupload","part":"14_尚硅谷_通用CRUD_@TableName注解","duration":281,"vid":"","weblink":"","dimension":{"width":1366,"height":768,"rotate":0}},{"cid":46903870,"page":15,"from":"vupload","part":"15_尚硅谷_通用CRUD_MP全局策略配置(1)","duration":546,"vid":"","weblink":"","dimension":{"width":1366,"height":768,"rotate":0}},{"cid":46903885,"page":16,"from":"vupload","part":"16_尚硅谷_通用CRUD_MP全局策略配置(2)","duration":280,"vid":"","weblink":"","dimension":{"width":1366,"height":768,"rotate":0}},{"cid":46903927,"page":17,"from":"vupload","part":"17_尚硅谷_通用CRUD_@TableField注解","duration":436,"vid":"","weblink":"","dimension":{"width":1366,"height":768,"rotate":0}},{"cid":46903955,"page":18,"from":"vupload","part":"18_尚硅谷_通用CRUD_插入数据获取主键值","duration":231,"vid":"","weblink":"","dimension":{"width":1366,"height":768,"rotate":0}},{"cid":46903995,"page":19,"from":"vupload","part":"19_尚硅谷_通用CRUD_insertAllColumn方法","duration":310,"vid":"","weblink":"","dimension":{"width":1366,"height":768,"rotate":0}},{"cid":46904010,"page":20,"from":"vupload","part":"20_尚硅谷_通用CRUD_updateById方法","duration":366,"vid":"","weblink":"","dimension":{"width":1366,"height":768,"rotate":0}},{"cid":46904043,"page":21,"from":"vupload","part":"21_尚硅谷_通用CRUD_updateAllColumnById方法","duration":174,"vid":"","weblink":"","dimension":{"width":1366,"height":768,"rotate":0}},{"cid":46904088,"page":22,"from":"vupload","part":"22_尚硅谷_通用CRUD_selectById方法","duration":195,"vid":"","weblink":"","dimension":{"width":1366,"height":768,"rotate":0}},{"cid":46904102,"page":23,"from":"vupload","part":"23_尚硅谷_通用CRUD_selectOne方法","duration":314,"vid":"","weblink":"","dimension":{"width":1366,"height":768,"rotate":0}},{"cid":46904120,"page":24,"from":"vupload","part":"24_尚硅谷_通用CRUD_selectBatchIds方法","duration":224,"vid":"","weblink":"","dimension":{"width":1366,"height":768,"rotate":0}},{"cid":46904162,"page":25,"from":"vupload","part":"25_尚硅谷_通用CRUD_selectByMap方法","duration":283,"vid":"","weblink":"","dimension":{"width":1366,"height":768,"rotate":0}},{"cid":46904196,"page":26,"from":"vupload","part":"26_尚硅谷_通用CRUD_selectPage方法","duration":450,"vid":"","weblink":"","dimension":{"width":1366,"height":768,"rotate":0}},{"cid":46904232,"page":27,"from":"vupload","part":"27_尚硅谷_通用CRUD_deleteById方法","duration":130,"vid":"","weblink":"","dimension":{"width":1366,"height":768,"rotate":0}},{"cid":46904288,"page":28,"from":"vupload","part":"28_尚硅谷_通用CRUD_deleteByMap方法","duration":192,"vid":"","weblink":"","dimension":{"width":1366,"height":768,"rotate":0}},{"cid":46904309,"page":29,"from":"vupload","part":"29_尚硅谷_通用CRUD_deleteBatchIds方法","duration":142,"vid":"","weblink":"","dimension":{"width":1366,"height":768,"rotate":0}},{"cid":46904331,"page":30,"from":"vupload","part":"30_尚硅谷_通用CRUD_MP启动注入SQL原理分析_提出问题","duration":287,"vid":"","weblink":"","dimension":{"width":1366,"height":768,"rotate":0}},{"cid":46904350,"page":31,"from":"vupload","part":"31_尚硅谷_通用CRUD_MP启动注入SQL原理分析_分析现象","duration":775,"vid":"","weblink":"","dimension":{"width":1366,"height":768,"rotate":0}},{"cid":46904377,"page":32,"from":"vupload","part":"32_尚硅谷_通用CRUD_MP启动注入SQL原理分析_分析关键步骤加断点","duration":197,"vid":"","weblink":"","dimension":{"width":1366,"height":768,"rotate":0}},{"cid":46904497,"page":33,"from":"vupload","part":"33_尚硅谷_通用CRUD_MP启动注入SQL原理分析_源码流程_关键对象总结","duration":1056,"vid":"","weblink":"","dimension":{"width":1366,"height":768,"rotate":0}},{"cid":46904526,"page":34,"from":"vupload","part":"34_尚硅谷_通用CRUD_小结","duration":315,"vid":"","weblink":"","dimension":{"width":1366,"height":768,"rotate":0}},{"cid":46904710,"page":35,"from":"vupload","part":"35_尚硅谷_条件构造器_EntityWrapper_Condition简介","duration":313,"vid":"","weblink":"","dimension":{"width":1366,"height":768,"rotate":0}},{"cid":46904769,"page":36,"from":"vupload","part":"36_尚硅谷_条件构造器_selectPage方法","duration":519,"vid":"","weblink":"","dimension":{"width":1366,"height":768,"rotate":0}},{"cid":46904814,"page":37,"from":"vupload","part":"37_尚硅谷_条件构造器_selectList方法","duration":353,"vid":"","weblink":"","dimension":{"width":1366,"height":768,"rotate":0}},{"cid":46904862,"page":38,"from":"vupload","part":"38_尚硅谷_条件构造器_update方法","duration":235,"vid":"","weblink":"","dimension":{"width":1366,"height":768,"rotate":0}},{"cid":46904893,"page":39,"from":"vupload","part":"39_尚硅谷_条件构造器_delete方法","duration":120,"vid":"","weblink":"","dimension":{"width":1366,"height":768,"rotate":0}},{"cid":46904912,"page":40,"from":"vupload","part":"40_尚硅谷_条件构造器_EntityWrapper常用方法","duration":443,"vid":"","weblink":"","dimension":{"width":1366,"height":768,"rotate":0}},{"cid":46904926,"page":41,"from":"vupload","part":"41_尚硅谷_条件构造器_Condition的用法","duration":234,"vid":"","weblink":"","dimension":{"width":1366,"height":768,"rotate":0}},{"cid":46904977,"page":42,"from":"vupload","part":"42_尚硅谷_条件构造器_小结","duration":175,"vid":"","weblink":"","dimension":{"width":1366,"height":768,"rotate":0}},{"cid":46904994,"page":43,"from":"vupload","part":"43_尚硅谷_AR_ActiveRecord简介","duration":87,"vid":"","weblink":"","dimension":{"width":1366,"height":768,"rotate":0}},{"cid":46905014,"page":44,"from":"vupload","part":"44_尚硅谷_AR_开启AR模式_实体类继承Model类","duration":212,"vid":"","weblink":"","dimension":{"width":1366,"height":768,"rotate":0}},{"cid":46905025,"page":45,"from":"vupload","part":"45_尚硅谷_AR_插入操作_insert方法","duration":272,"vid":"","weblink":"","dimension":{"width":1366,"height":768,"rotate":0}},{"cid":46905057,"page":46,"from":"vupload","part":"46_尚硅谷_AR_修改操作_updateById方法","duration":142,"vid":"","weblink":"","dimension":{"width":1366,"height":768,"rotate":0}},{"cid":46905081,"page":47,"from":"vupload","part":"47_尚硅谷_AR_查询操作_selectById方法","duration":146,"vid":"","weblink":"","dimension":{"width":1366,"height":768,"rotate":0}},{"cid":46905105,"page":48,"from":"vupload","part":"48_尚硅谷_AR_查询操作_selectAll方法","duration":60,"vid":"","weblink":"","dimension":{"width":1366,"height":768,"rotate":0}},{"cid":46905124,"page":49,"from":"vupload","part":"49_尚硅谷_AR_查询操作_selectList_selectCount方法","duration":228,"vid":"","weblink":"","dimension":{"width":1366,"height":768,"rotate":0}},{"cid":46905132,"page":50,"from":"vupload","part":"50_尚硅谷_AR_删除操作_deleteById方法","duration":270,"vid":"","weblink":"","dimension":{"width":1366,"height":768,"rotate":0}},{"cid":46905161,"page":51,"from":"vupload","part":"51_尚硅谷_AR_删除操作_delete方法","duration":128,"vid":"","weblink":"","dimension":{"width":1366,"height":768,"rotate":0}},{"cid":46905190,"page":52,"from":"vupload","part":"52_尚硅谷_AR_删除操作_selectPage分页复杂操作","duration":264,"vid":"","weblink":"","dimension":{"width":1366,"height":768,"rotate":0}},{"cid":46905202,"page":53,"from":"vupload","part":"53_尚硅谷_AR_小结","duration":268,"vid":"","weblink":"","dimension":{"width":1366,"height":768,"rotate":0}},{"cid":46905228,"page":54,"from":"vupload","part":"54_尚硅谷_代码生成器_MP与MBG的简单对比","duration":244,"vid":"","weblink":"","dimension":{"width":1366,"height":768,"rotate":0}},{"cid":46905250,"page":55,"from":"vupload","part":"55_尚硅谷_代码生成器_需要注意的一些问题","duration":225,"vid":"","weblink":"","dimension":{"width":1366,"height":768,"rotate":0}},{"cid":46905271,"page":56,"from":"vupload","part":"56_尚硅谷_代码生成器_加入依赖信息","duration":152,"vid":"","weblink":"","dimension":{"width":1366,"height":768,"rotate":0}},{"cid":46905298,"page":57,"from":"vupload","part":"57_尚硅谷_代码生成器_GlobalConfig全局配置编码","duration":528,"vid":"","weblink":"","dimension":{"width":1366,"height":768,"rotate":0}},{"cid":46905311,"page":58,"from":"vupload","part":"58_尚硅谷_代码生成器_DataSourceConfig数据源配置编码","duration":122,"vid":"","weblink":"","dimension":{"width":1366,"height":768,"rotate":0}},{"cid":46905363,"page":59,"from":"vupload","part":"59_尚硅谷_代码生成器_StrategyConfig策略配置编码","duration":211,"vid":"","weblink":"","dimension":{"width":1366,"height":768,"rotate":0}},{"cid":46905378,"page":60,"from":"vupload","part":"60_尚硅谷_代码生成器_PackageConfig包名策略配置","duration":184,"vid":"","weblink":"","dimension":{"width":1366,"height":768,"rotate":0}},{"cid":46905411,"page":61,"from":"vupload","part":"61_尚硅谷_代码生成器_AutoGenerator整合配置","duration":100,"vid":"","weblink":"","dimension":{"width":1366,"height":768,"rotate":0}},{"cid":46905424,"page":62,"from":"vupload","part":"62_尚硅谷_代码生成器_测试生成_生成代码解析","duration":567,"vid":"","weblink":"","dimension":{"width":1366,"height":768,"rotate":0}},{"cid":46905441,"page":63,"from":"vupload","part":"63_尚硅谷_代码生成器-小结","duration":153,"vid":"","weblink":"","dimension":{"width":1366,"height":768,"rotate":0}},{"cid":46905487,"page":64,"from":"vupload","part":"64_尚硅谷_插件扩展_MyBatis插件机制简介","duration":374,"vid":"","weblink":"","dimension":{"width":1366,"height":768,"rotate":0}},{"cid":46905508,"page":65,"from":"vupload","part":"65_尚硅谷_插件扩展_PaginationInterceptor分页插件","duration":1022,"vid":"","weblink":"","dimension":{"width":1366,"height":768,"rotate":0}},{"cid":46905542,"page":66,"from":"vupload","part":"66_尚硅谷_插件扩展_注册分页插件后Page对象的使用","duration":324,"vid":"","weblink":"","dimension":{"width":1366,"height":768,"rotate":0}},{"cid":46905639,"page":67,"from":"vupload","part":"67_尚硅谷_插件扩展_SqlExplainInterceptor 执行分析插件","duration":272,"vid":"","weblink":"","dimension":{"width":1366,"height":768,"rotate":0}},{"cid":46905673,"page":68,"from":"vupload","part":"68_尚硅谷_插件扩展_SqlExplainInterceptor 执行分析插件执行原理分析","duration":337,"vid":"","weblink":"","dimension":{"width":1366,"height":768,"rotate":0}},{"cid":46905709,"page":69,"from":"vupload","part":"69_尚硅谷_插件扩展_PerformanceInterceptor性能分析插件","duration":549,"vid":"","weblink":"","dimension":{"width":1366,"height":768,"rotate":0}},{"cid":46905744,"page":70,"from":"vupload","part":"70_尚硅谷_插件扩展_OptimisticLockerInterceptor乐观锁插件","duration":644,"vid":"","weblink":"","dimension":{"width":1366,"height":768,"rotate":0}},{"cid":46905790,"page":71,"from":"vupload","part":"71_尚硅谷_自定义全局操作_简介","duration":165,"vid":"","weblink":"","dimension":{"width":1366,"height":768,"rotate":0}},{"cid":46905840,"page":72,"from":"vupload","part":"72_尚硅谷_自定义全局操作_步骤","duration":373,"vid":"","weblink":"","dimension":{"width":1366,"height":768,"rotate":0}},{"cid":46905857,"page":73,"from":"vupload","part":"73_尚硅谷_自定义全局操作_inject方法的编写_添加MappedStatement","duration":400,"vid":"","weblink":"","dimension":{"width":1366,"height":768,"rotate":0}},{"cid":46905903,"page":74,"from":"vupload","part":"74_尚硅谷_自定义全局操作_总结","duration":198,"vid":"","weblink":"","dimension":{"width":1366,"height":768,"rotate":0}},{"cid":46905941,"page":75,"from":"vupload","part":"75_尚硅谷_全局Sql注入器应用_逻辑删除_简介","duration":257,"vid":"","weblink":"","dimension":{"width":1366,"height":768,"rotate":0}},{"cid":46905961,"page":76,"from":"vupload","part":"76_尚硅谷_全局Sql注入器应用_逻辑删除_配置","duration":446,"vid":"","weblink":"","dimension":{"width":1366,"height":768,"rotate":0}},{"cid":46905980,"page":77,"from":"vupload","part":"77_尚硅谷_全局Sql注入器应用_逻辑删除_测试","duration":282,"vid":"","weblink":"","dimension":{"width":1366,"height":768,"rotate":0}},{"cid":46906013,"page":78,"from":"vupload","part":"78_尚硅谷_全局Sql注入器应用_逻辑删除_源码分析","duration":175,"vid":"","weblink":"","dimension":{"width":1366,"height":768,"rotate":0}},{"cid":46906043,"page":79,"from":"vupload","part":"79_尚硅谷_公共字段自动填充_元数据处理器接口简介","duration":381,"vid":"","weblink":"","dimension":{"width":1366,"height":768,"rotate":0}},{"cid":46906066,"page":80,"from":"vupload","part":"80_尚硅谷_公共字段自动填充_实现步骤","duration":363,"vid":"","weblink":"","dimension":{"width":1366,"height":768,"rotate":0}},{"cid":46906100,"page":81,"from":"vupload","part":"81_尚硅谷_公共字段自动填充_自定义填充处理器的实现","duration":224,"vid":"","weblink":"","dimension":{"width":1366,"height":768,"rotate":0}},{"cid":46906132,"page":82,"from":"vupload","part":"82_尚硅谷_公共字段自动填充_测试","duration":309,"vid":"","weblink":"","dimension":{"width":1366,"height":768,"rotate":0}},{"cid":46906160,"page":83,"from":"vupload","part":"83_尚硅谷_Oracle数据库主键Sequence简介","duration":167,"vid":"","weblink":"","dimension":{"width":1366,"height":768,"rotate":0}},{"cid":46906183,"page":84,"from":"vupload","part":"84_尚硅谷_Oracle环境搭建_Oracle驱动依赖的问题","duration":228,"vid":"","weblink":"","dimension":{"width":1366,"height":768,"rotate":0}},{"cid":46906208,"page":85,"from":"vupload","part":"85_尚硅谷_Oracle环境搭建_配置连接信息","duration":169,"vid":"","weblink":"","dimension":{"width":1366,"height":768,"rotate":0}},{"cid":46906237,"page":86,"from":"vupload","part":"86_尚硅谷_Oracle环境搭建_创建表及序列","duration":328,"vid":"","weblink":"","dimension":{"width":1366,"height":768,"rotate":0}},{"cid":46906262,"page":87,"from":"vupload","part":"87_尚硅谷_Oracle主键Sequence使用配置","duration":246,"vid":"","weblink":"","dimension":{"width":1366,"height":768,"rotate":0}},{"cid":46906286,"page":88,"from":"vupload","part":"88_尚硅谷_Oracle主键Sequence_测试","duration":191,"vid":"","weblink":"","dimension":{"width":1366,"height":768,"rotate":0}},{"cid":46906301,"page":89,"from":"vupload","part":"89_尚硅谷_Oracle主键Sequence_多个实体类公用一个序列","duration":207,"vid":"","weblink":"","dimension":{"width":1366,"height":768,"rotate":0}},{"cid":46906325,"page":90,"from":"vupload","part":"90_尚硅谷_Idea快速开发插件","duration":348,"vid":"","weblink":"","dimension":{"width":1366,"height":768,"rotate":0}}],"subtitle":{"allow_submit":false,"list":[]},"is_season_display":false,"user_garb":{"url_image_ani_cut":""},"honor_reply":{},"like_icon":"","need_jump_bv":false,"disable_show_up_info":false}}