{"code":0,"message":"0","ttl":1,"data":{"bvid":"BV1H44y1x76X","aid":976047422,"videos":31,"tid":231,"tname":"计算机技术","copyright":1,"pic":"http://i2.hdslb.com/bfs/archive/e3606d85c0629ba2dcd0e67c906dfec0edc5faba.jpg","title":"【尚硅谷】Alibaba开源数据同步工具DataX技术教程","pubdate":1634083216,"ctime":1634083222,"desc":"求三连呀【点赞、投币、收藏】感谢支持~\n教程附赠全部配套的课件和软件，如何下载请看该教程第一集：BV1Kb411W75N\n本套视频教程从DataX安装部署开始讲起，详细讲解了MySQL、Oracle、MongoDB、SQLServer、DB2等数据库的数据同步操作，且不囿于安装操作，更深入内核源码，解读数据同步的执行流程，并对DataX的使用优化进行深入调研，提供了多种常见优化方案。一套教程，带你轻松玩转DataX！","desc_v2":[{"raw_text":"求三连呀【点赞、投币、收藏】感谢支持~\n教程附赠全部配套的课件和软件，如何下载请看该教程第一集：BV1Kb411W75N\n本套视频教程从DataX安装部署开始讲起，详细讲解了MySQL、Oracle、MongoDB、SQLServer、DB2等数据库的数据同步操作，且不囿于安装操作，更深入内核源码，解读数据同步的执行流程，并对DataX的使用优化进行深入调研，提供了多种常见优化方案。一套教程，带你轻松玩转DataX！","type":1,"biz_id":0}],"state":0,"duration":17654,"rights":{"bp":0,"elec":0,"download":1,"movie":0,"pay":0,"hd5":0,"no_reprint":1,"autoplay":1,"ugc_pay":0,"is_cooperation":0,"ugc_pay_preview":0,"no_background":0,"clean_mode":0,"is_stein_gate":0,"is_360":0,"no_share":0,"arc_pay":0,"free_watch":0},"owner":{"mid":302417610,"name":"尚硅谷","face":"https://i0.hdslb.com/bfs/face/aabb00d3fa8b1526879ee5fc3875c5f543100aa2.jpg"},"stat":{"aid":976047422,"view":105939,"danmaku":440,"reply":215,"favorite":5711,"coin":1148,"share":560,"now_rank":0,"his_rank":0,"like":1617,"dislike":0,"evaluation":"","argue_msg":"","vt":0},"dynamic":"来 了 来 了 ~\nAre you ok ？","cid":423887738,"dimension":{"width":1920,"height":1040,"rotate":0},"premiere":null,"teenage_mode":0,"is_chargeable_season":false,"is_story":false,"is_upower_exclusive":false,"is_upower_play":false,"enable_vt":0,"vt_display":"","no_cache":false,"pages":[{"cid":423887738,"page":1,"from":"vupload","part":"01_DataX_课程简介","duration":360,"vid":"","weblink":"","dimension":{"width":1920,"height":1040,"rotate":0},"first_frame":"http://i1.hdslb.com/bfs/storyff/n211012a239flr6abmldr1h4936ov3nr_firsti.jpg"},{"cid":423891061,"page":2,"from":"vupload","part":"02_DataX_概述","duration":641,"vid":"","weblink":"","dimension":{"width":1920,"height":1040,"rotate":0},"first_frame":"http://i2.hdslb.com/bfs/storyff/n211012a22883fudu8gpt935yqzpw7f9_firsti.jpg"},{"cid":423891134,"page":3,"from":"vupload","part":"03_DataX_原理","duration":487,"vid":"","weblink":"","dimension":{"width":1920,"height":1040,"rotate":0},"first_frame":"http://i1.hdslb.com/bfs/storyff/n211012a21z6g68f71w2g11ml2nr1tq8_firsti.jpg"},{"cid":423891302,"page":4,"from":"vupload","part":"04_DataX_与Sqoop的对比","duration":704,"vid":"","weblink":"","dimension":{"width":1920,"height":1040,"rotate":0},"first_frame":"http://i1.hdslb.com/bfs/storyff/n211012a23dlwtb9mooc2j3dttc0ft5d_firsti.jpg"},{"cid":423891377,"page":5,"from":"vupload","part":"05_DataX_安装\u0026体验","duration":765,"vid":"","weblink":"","dimension":{"width":1920,"height":1040,"rotate":0},"first_frame":"http://i2.hdslb.com/bfs/storyff/n211012a214ibhzbk1swb3249e5e2iw4_firsti.jpg"},{"cid":423891563,"page":6,"from":"vupload","part":"06_DataX_案例_StreamReader\u0026StreamWriter","duration":880,"vid":"","weblink":"","dimension":{"width":1920,"height":1040,"rotate":0},"first_frame":"http://i0.hdslb.com/bfs/storyff/n211012a22hs6n3pw1xhujelp9k8cc60_firsti.jpg"},{"cid":423891758,"page":7,"from":"vupload","part":"07_DataX_案例_mysql2hdfs","duration":1355,"vid":"","weblink":"","dimension":{"width":1920,"height":1040,"rotate":0},"first_frame":"http://i2.hdslb.com/bfs/storyff/n211012a22zfoy714bmit822rrf7x3w0_firsti.jpg"},{"cid":423891966,"page":8,"from":"vupload","part":"08_DataX_案例_HDFS高可用配置","duration":234,"vid":"","weblink":"","dimension":{"width":1920,"height":1040,"rotate":0},"first_frame":"http://i0.hdslb.com/bfs/storyff/n211012a29zdq1yba79ljn2ectrnq8in_firsti.jpg"},{"cid":423892000,"page":9,"from":"vupload","part":"09_DataX_案例_hdfs2mysql","duration":510,"vid":"","weblink":"","dimension":{"width":1920,"height":1040,"rotate":0},"first_frame":"http://i1.hdslb.com/bfs/storyff/n211012a2l2t80kxna13mnhcdny0vgr7_firsti.jpg"},{"cid":423892103,"page":10,"from":"vupload","part":"10_DataX_Oracle安装准备工作","duration":1202,"vid":"","weblink":"","dimension":{"width":1920,"height":1040,"rotate":0},"first_frame":"http://i2.hdslb.com/bfs/storyff/n211012a23esegrz6itiv2484eb8mvcm_firsti.jpg"},{"cid":423892614,"page":11,"from":"vupload","part":"11_DataX_图形化安装Oracle","duration":428,"vid":"","weblink":"","dimension":{"width":1920,"height":1040,"rotate":0},"first_frame":"http://i2.hdslb.com/bfs/storyff/n211012a23g9kwnn2t7aet1okxmedhxe_firsti.jpg"},{"cid":423892668,"page":12,"from":"vupload","part":"12_DataX_Oracle创建数据库","duration":409,"vid":"","weblink":"","dimension":{"width":1920,"height":1040,"rotate":0},"first_frame":"http://i1.hdslb.com/bfs/storyff/n211012a2340uq4to27yg43fh10ohy4d_firsti.jpg"},{"cid":423892729,"page":13,"from":"vupload","part":"13_DataX_Oracle简单使用","duration":484,"vid":"","weblink":"","dimension":{"width":1920,"height":1040,"rotate":0},"first_frame":"http://i2.hdslb.com/bfs/storyff/n211012a23d9hdcdtixqpiy5gnhcmwkt_firsti.jpg"},{"cid":423892791,"page":14,"from":"vupload","part":"14_DataX_案例_Oracle导出到MySQL和HDFS","duration":717,"vid":"","weblink":"","dimension":{"width":1920,"height":1040,"rotate":0},"first_frame":"http://i0.hdslb.com/bfs/storyff/n211012a238tqrvwqihrb52i0rz0a4kw_firsti.jpg"},{"cid":423892929,"page":15,"from":"vupload","part":"15_DataX_MongoDB简单介绍","duration":482,"vid":"","weblink":"","dimension":{"width":1920,"height":1040,"rotate":0},"first_frame":"http://i0.hdslb.com/bfs/storyff/n211012a23m6yhn5doiglb32x6fmqnkp_firsti.jpg"},{"cid":423892997,"page":16,"from":"vupload","part":"16_DataX_MongoDB安装\u0026简单使用","duration":951,"vid":"","weblink":"","dimension":{"width":1920,"height":1040,"rotate":0},"first_frame":"http://i1.hdslb.com/bfs/storyff/n211012a21xvxpzkjkd5cp2txtnr97yh_firsti.jpg"},{"cid":423891130,"page":17,"from":"vupload","part":"17_DataX_案例_MongoDB导出到MySQL和HDFS","duration":630,"vid":"","weblink":"","dimension":{"width":1920,"height":1040,"rotate":0},"first_frame":"http://i0.hdslb.com/bfs/storyff/n211012a23473pzrjmsm9z20guki0tct_firsti.jpg"},{"cid":423893216,"page":18,"from":"vupload","part":"18_DataX_SQLServer简介\u0026安装","duration":634,"vid":"","weblink":"","dimension":{"width":1920,"height":1040,"rotate":0},"first_frame":"http://i2.hdslb.com/bfs/storyff/n211012a2iiuplyjypvz91f5bwxi2z0o_firsti.jpg"},{"cid":423893400,"page":19,"from":"vupload","part":"19_DataX_SQLServer客户端安装\u0026简单使用","duration":520,"vid":"","weblink":"","dimension":{"width":1920,"height":1040,"rotate":0},"first_frame":"http://i1.hdslb.com/bfs/storyff/n211012a22v0y04yfja4y63b1ho1lfrc_firsti.jpg"},{"cid":423893485,"page":20,"from":"vupload","part":"20_DataX_案例_SQLServer导出到MySQL和HDFS","duration":343,"vid":"","weblink":"","dimension":{"width":1920,"height":1040,"rotate":0},"first_frame":"http://i0.hdslb.com/bfs/storyff/n211012a232u905sizmc3e2a9icbmpic_firsti.jpg"},{"cid":423893539,"page":21,"from":"vupload","part":"21_DataX_DB2简介\u0026安装准备","duration":287,"vid":"","weblink":"","dimension":{"width":1920,"height":1040,"rotate":0},"first_frame":"http://i1.hdslb.com/bfs/storyff/n211012a2101hb6qmcgwz4yz41rthd7g_firsti.jpg"},{"cid":423893605,"page":22,"from":"vupload","part":"22_DataX_DB2安装","duration":401,"vid":"","weblink":"","dimension":{"width":1920,"height":1040,"rotate":0},"first_frame":"http://i1.hdslb.com/bfs/storyff/n211012a259756pgbuhg7lndzafowbpv_firsti.jpg"},{"cid":423893648,"page":23,"from":"vupload","part":"23_DataX_DB2启动\u0026简单使用","duration":259,"vid":"","weblink":"","dimension":{"width":1920,"height":1040,"rotate":0},"first_frame":"http://i0.hdslb.com/bfs/storyff/n211012a2hivaxkxjyntt38tvfx89ag5_firsti.jpg"},{"cid":423893699,"page":24,"from":"vupload","part":"24_DataX_案例_DB2导出到HDFS和MySQL","duration":731,"vid":"","weblink":"","dimension":{"width":1920,"height":1040,"rotate":0},"first_frame":"http://i1.hdslb.com/bfs/storyff/n211012a2pvvj615hlo731oezsvfw24s_firsti.jpg"},{"cid":423893814,"page":25,"from":"vupload","part":"25_DataX_源码分析_总体流程认识\u0026程序入口","duration":398,"vid":"","weblink":"","dimension":{"width":1920,"height":1040,"rotate":0},"first_frame":"http://i2.hdslb.com/bfs/storyff/n211012a217bpjwlxz80ki2lwcrykd0j_firsti.jpg"},{"cid":423893870,"page":26,"from":"vupload","part":"26_DataX_源码分析_并发数的确定","duration":767,"vid":"","weblink":"","dimension":{"width":1920,"height":1040,"rotate":0},"first_frame":"http://i0.hdslb.com/bfs/storyff/n211012a22f3bbd6299jow2wihcn7b0i_firsti.jpg"},{"cid":423894055,"page":27,"from":"vupload","part":"27_DataX_源码分析_切分简单了解","duration":121,"vid":"","weblink":"","dimension":{"width":1920,"height":1040,"rotate":0},"first_frame":"http://i2.hdslb.com/bfs/storyff/n211012a222p22zkils04q2q9ppy039y_firsti.jpg"},{"cid":423894163,"page":28,"from":"vupload","part":"28_DataX_源码分析_调度_确定组数\u0026分组算法","duration":441,"vid":"","weblink":"","dimension":{"width":1920,"height":1040,"rotate":0},"first_frame":"http://i1.hdslb.com/bfs/storyff/n211012a21tspwu2f498f16rywb7l5lb_firsti.jpg"},{"cid":423894326,"page":29,"from":"vupload","part":"29_DataX_源码分析_调度_调度实现","duration":315,"vid":"","weblink":"","dimension":{"width":1920,"height":1040,"rotate":0},"first_frame":"http://i1.hdslb.com/bfs/storyff/n211012a22zz3ofyul5dnna8i99krlx0_firsti.jpg"},{"cid":423894372,"page":30,"from":"vupload","part":"30_DataX_源码分析_数据传输_限速的实现","duration":715,"vid":"","weblink":"","dimension":{"width":1920,"height":1040,"rotate":0},"first_frame":"http://i2.hdslb.com/bfs/storyff/n211012a22fmon27lmrujv2j4m70h2lb_firsti.jpg"},{"cid":423894574,"page":31,"from":"vupload","part":"31_DataX_优化","duration":483,"vid":"","weblink":"","dimension":{"width":1920,"height":1040,"rotate":0},"first_frame":"http://i2.hdslb.com/bfs/storyff/n211012a22zxntvhex0dcx1tasi3b00u_firsti.jpg"}],"subtitle":{"allow_submit":false,"list":[]},"is_season_display":false,"user_garb":{"url_image_ani_cut":""},"honor_reply":{},"like_icon":"","need_jump_bv":false,"disable_show_up_info":false}}